{"chapter":"4","verses":{"1":[{"tl":"Iēsous","en":"Jesus","gr":"Ἰησοῦς","pu":null,"pa":"N-NMS","st":"2424"},{"tl":"de","en":"then","gr":"δὲ","pu":",","pa":"Conj","st":"1161"},{"tl":"plērēs","en":"full","gr":"πλήρης","pu":null,"pa":"Adj-NMS","st":"4134"},{"tl":"Pneumatos","en":"of [the] Spirit","gr":"Πνεύματος","pu":null,"pa":"N-GNS","st":"4151"},{"tl":"Hagiou","en":"Holy","gr":"Ἁγίου","pu":",","pa":"Adj-GNS","st":"40"},{"tl":"hypestrepsen","en":"returned","gr":"ὑπέστρεψεν","pu":null,"pa":"V-AIA-3S","st":"5290"},{"tl":"apo","en":"from","gr":"ἀπὸ","pu":null,"pa":"Prep","st":"575"},{"tl":"tou","en":"the","gr":"τοῦ","pu":null,"pa":"Art-GMS","st":"3588"},{"tl":"Iordanou","en":"Jordan","gr":"Ἰορδάνου","pu":null,"pa":"N-GMS","st":"2446"},{"tl":"kai","en":"and","gr":"καὶ","pu":null,"pa":"Conj","st":"2532"},{"tl":"ēgeto","en":"was led","gr":"ἤγετο","pu":null,"pa":"V-IIM/P-3S","st":"71"},{"tl":"en","en":"by","gr":"ἐν","pu":null,"pa":"Prep","st":"1722"},{"tl":"tō","en":"the","gr":"τῷ","pu":null,"pa":"Art-DNS","st":"3588"},{"tl":"Pneumati","en":"Spirit","gr":"Πνεύματι","pu":null,"pa":"N-DNS","st":"4151"},{"tl":"en","en":"into","gr":"ἐν","pu":null,"pa":"Prep","st":"1722"},{"tl":"tē","en":"the","gr":"τῇ","pu":null,"pa":"Art-DFS","st":"3588"},{"tl":"erēmō","en":"wilderness","gr":"ἐρήμῳ","pu":",","pa":"Adj-DFS","st":"2048"}],"2":[{"tl":"hēmeras","en":"days","gr":"ἡμέρας","pu":null,"pa":"N-AFP","st":"2250"},{"tl":"tesserakonta","en":"forty","gr":"τεσσεράκοντα","pu":null,"pa":"Adj-AFP","st":"5062"},{"tl":"peirazomenos","en":"being tempted","gr":"πειραζόμενος","pu":null,"pa":"V-PPM/P-NMS","st":"3985"},{"tl":"hypo","en":"by","gr":"ὑπὸ","pu":null,"pa":"Prep","st":"5259"},{"tl":"tou","en":"the","gr":"τοῦ","pu":null,"pa":"Art-GMS","st":"3588"},{"tl":"diabolou","en":"devil","gr":"διαβόλου","pu":".","pa":"Adj-GMS","st":"1228"},{"tl":"Kai","en":"And","gr":"Καὶ","pu":null,"pa":"Conj","st":"2532"},{"tl":"ouk","en":"not","gr":"οὐκ","pu":null,"pa":"Adv","st":"3756"},{"tl":"ephagen","en":"He ate","gr":"ἔφαγεν","pu":null,"pa":"V-AIA-3S","st":"5315"},{"tl":"ouden","en":"nothing","gr":"οὐδὲν","pu":null,"pa":"Adj-ANS","st":"3762"},{"tl":"en","en":"in","gr":"ἐν","pu":null,"pa":"Prep","st":"1722"},{"tl":"tais","en":"the","gr":"ταῖς","pu":null,"pa":"Art-DFP","st":"3588"},{"tl":"hēmerais","en":"days","gr":"ἡμέραις","pu":null,"pa":"N-DFP","st":"2250"},{"tl":"ekeinais","en":"those","gr":"ἐκείναις","pu":",","pa":"DPro-DFP","st":"1565"},{"tl":"kai","en":"and","gr":"καὶ","pu":null,"pa":"Conj","st":"2532"},{"tl":"syntelestheisōn","en":"having ended","gr":"συντελεσθεισῶν","pu":null,"pa":"V-APP-GFP","st":"4931"},{"tl":"autōn","en":"they","gr":"αὐτῶν","pu":",","pa":"PPro-GF3P","st":"846"},{"tl":"epeinasen","en":"He was hungry","gr":"ἐπείνασεν","pu":".","pa":"V-AIA-3S","st":"3983"}],"3":[{"tl":"Eipen","en":"Said","gr":"Εἶπεν","pu":null,"pa":"V-AIA-3S","st":"2036"},{"tl":"de","en":"then","gr":"δὲ","pu":null,"pa":"Conj","st":"1161"},{"tl":"autō","en":"to Him","gr":"αὐτῷ","pu":null,"pa":"PPro-DM3S","st":"846"},{"tl":"ho","en":"the","gr":"ὁ","pu":null,"pa":"Art-NMS","st":"3588"},{"tl":"diabolos","en":"devil","gr":"διάβολος","pu":",","pa":"Adj-NMS","st":"1228"},{"tl":"Ei","en":"If","gr":"Εἰ","pu":null,"pa":"Conj","st":"1487"},{"tl":"Huios","en":"[the] Son","gr":"Υἱὸς","pu":null,"pa":"N-NMS","st":"5207"},{"tl":"ei","en":"You are","gr":"εἶ","pu":null,"pa":"V-PIA-2S","st":"1510"},{"tl":"tou","en":" - ","gr":"τοῦ","pu":null,"pa":"Art-GMS","st":"3588"},{"tl":"Theou","en":"of God","gr":"Θεοῦ","pu":",","pa":"N-GMS","st":"2316"},{"tl":"eipe","en":"speak","gr":"εἰπὲ","pu":null,"pa":"V-AMA-2S","st":"2036"},{"tl":"tō","en":"to the","gr":"τῷ","pu":null,"pa":"Art-DMS","st":"3588"},{"tl":"lithō","en":"stone","gr":"λίθῳ","pu":null,"pa":"N-DMS","st":"3037"},{"tl":"toutō","en":"this","gr":"τούτῳ","pu":",","pa":"DPro-DMS","st":"3778"},{"tl":"hina","en":"that","gr":"ἵνα","pu":null,"pa":"Conj","st":"2443"},{"tl":"genētai","en":"it should become","gr":"γένηται","pu":null,"pa":"V-ASM-3S","st":"1096"},{"tl":"artos","en":"bread","gr":"ἄρτος","pu":".","pa":"N-NMS","st":"740"}],"4":[{"tl":"Kai","en":"And","gr":"Καὶ","pu":null,"pa":"Conj","st":"2532"},{"tl":"apekrithē","en":"answered","gr":"ἀπεκρίθη","pu":null,"pa":"V-AIP-3S","st":"611"},{"tl":"pros","en":"to","gr":"πρὸς","pu":null,"pa":"Prep","st":"4314"},{"tl":"auton","en":"him","gr":"αὐτὸν","pu":null,"pa":"PPro-AM3S","st":"846"},{"tl":"ho","en":" - ","gr":"ὁ","pu":null,"pa":"Art-NMS","st":"3588"},{"tl":"Iēsous","en":"Jesus","gr":"Ἰησοῦς","pu":",","pa":"N-NMS","st":"2424"},{"tl":"Gegraptai","en":"It has been written","gr":"Γέγραπται","pu":null,"pa":"V-RIM/P-3S","st":"1125"},{"tl":"hoti","en":" - ","gr":"ὅτι","pu":":","pa":"Conj","st":"3754"},{"tl":"Ouk","en":"Not","gr":"Οὐκ","pu":null,"pa":"Adv","st":"3756"},{"tl":"ep’","en":"on","gr":"ἐπ’","pu":null,"pa":"Prep","st":"1909"},{"tl":"artō","en":"bread","gr":"ἄρτῳ","pu":null,"pa":"N-DMS","st":"740"},{"tl":"monō","en":"alone","gr":"μόνῳ","pu":null,"pa":"Adj-DMS","st":"3441"},{"tl":"zēsetai","en":"shall live","gr":"ζήσεται","pu":null,"pa":"V-FIM-3S","st":"2198"},{"tl":"ho","en":"the","gr":"ὁ","pu":null,"pa":"Art-NMS","st":"3588"},{"tl":"anthrōpos","en":"man","gr":"ἄνθρωπος","pu":".","pa":"N-NMS","st":"444"},{"tl":"all’","en":"but","gr":"⧼ἀλλ’","pu":null,"pa":"Conj","st":"235"},{"tl":"epi","en":"by","gr":"ἐπὶ","pu":null,"pa":"Prep","st":"1909"},{"tl":"panti","en":"every","gr":"παντὶ","pu":null,"pa":"Adj-DMS","st":"3956"},{"tl":"rhēmati","en":"word","gr":"ῥήματι","pu":null,"pa":"N-DNS","st":"4487"},{"tl":"theou","en":"of God","gr":"θεοῦ⧽","pu":".","pa":"N-GMS","st":"2316"}],"5":[{"tl":"Kai","en":"And","gr":"Καὶ","pu":null,"pa":"Conj","st":"2532"},{"tl":"anagagōn","en":"having led up","gr":"ἀναγαγὼν","pu":null,"pa":"V-APA-NMS","st":"321"},{"tl":"auton","en":"Him","gr":"αὐτὸν","pu":",","pa":"PPro-AM3S","st":"846"},{"tl":"ho","en":"the","gr":"⧼ὁ","pu":null,"pa":"Art-NMS","st":"3588"},{"tl":"diabolos","en":"devil","gr":"διάβολος","pu":null,"pa":"Adj-NMS","st":"1228"},{"tl":"eis","en":"into","gr":"εἰς","pu":null,"pa":"Prep","st":"1519"},{"tl":"oros","en":"a mountain","gr":"ὄρος","pu":null,"pa":"N-ANS","st":"3735"},{"tl":"hypsēlon","en":"high","gr":"ὑψηλὸν⧽","pu":",","pa":"Adj-NNS","st":"5308"},{"tl":"edeixen","en":"he showed","gr":"ἔδειξεν","pu":null,"pa":"V-AIA-3S","st":"1166"},{"tl":"autō","en":"Him","gr":"αὐτῷ","pu":null,"pa":"PPro-DM3S","st":"846"},{"tl":"pasas","en":"all","gr":"πάσας","pu":null,"pa":"Adj-AFP","st":"3956"},{"tl":"tas","en":"the","gr":"τὰς","pu":null,"pa":"Art-AFP","st":"3588"},{"tl":"basileias","en":"kingdoms","gr":"βασιλείας","pu":null,"pa":"N-AFP","st":"932"},{"tl":"tēs","en":"of the","gr":"τῆς","pu":null,"pa":"Art-GFS","st":"3588"},{"tl":"oikoumenēs","en":"world","gr":"οἰκουμένης","pu":null,"pa":"N-GFS","st":"3625"},{"tl":"en","en":"in","gr":"ἐν","pu":null,"pa":"Prep","st":"1722"},{"tl":"stigmē","en":"a moment","gr":"στιγμῇ","pu":null,"pa":"N-DFS","st":"4743"},{"tl":"chronou","en":"of time","gr":"χρόνου","pu":".","pa":"N-GMS","st":"5550"}],"6":[{"tl":"kai","en":"And","gr":"καὶ","pu":null,"pa":"Conj","st":"2532"},{"tl":"eipen","en":"said","gr":"εἶπεν","pu":null,"pa":"V-AIA-3S","st":"2036"},{"tl":"autō","en":"to Him","gr":"αὐτῷ","pu":null,"pa":"PPro-DM3S","st":"846"},{"tl":"ho","en":"the","gr":"ὁ","pu":null,"pa":"Art-NMS","st":"3588"},{"tl":"diabolos","en":"devil","gr":"διάβολος","pu":",","pa":"Adj-NMS","st":"1228"},{"tl":"Soi","en":"To You","gr":"Σοὶ","pu":null,"pa":"PPro-D2S","st":"4771"},{"tl":"dōsō","en":"will I give","gr":"δώσω","pu":null,"pa":"V-FIA-1S","st":"1325"},{"tl":"tēn","en":"the","gr":"τὴν","pu":null,"pa":"Art-AFS","st":"3588"},{"tl":"exousian","en":"authority","gr":"ἐξουσίαν","pu":null,"pa":"N-AFS","st":"1849"},{"tl":"tautēn","en":"this","gr":"ταύτην","pu":null,"pa":"DPro-AFS","st":"3778"},{"tl":"hapasan","en":"all","gr":"ἅπασαν","pu":",","pa":"Adj-AFS","st":"537"},{"tl":"kai","en":"and","gr":"καὶ","pu":null,"pa":"Conj","st":"2532"},{"tl":"tēn","en":"the","gr":"τὴν","pu":null,"pa":"Art-AFS","st":"3588"},{"tl":"doxan","en":"glory","gr":"δόξαν","pu":null,"pa":"N-AFS","st":"1391"},{"tl":"autōn","en":"of it","gr":"αὐτῶν","pu":";","pa":"PPro-GF3P","st":"846"},{"tl":"hoti","en":"for","gr":"ὅτι","pu":null,"pa":"Conj","st":"3754"},{"tl":"emoi","en":"to me","gr":"ἐμοὶ","pu":null,"pa":"PPro-D1S","st":"1473"},{"tl":"paradedotai","en":"it has been delivered","gr":"παραδέδοται","pu":",","pa":"V-RIM/P-3S","st":"3860"},{"tl":"kai","en":"and","gr":"καὶ","pu":null,"pa":"Conj","st":"2532"},{"tl":"hō","en":"to whom","gr":"ᾧ","pu":null,"pa":"RelPro-DMS","st":"3739"},{"tl":"ean","en":"if","gr":"ἐὰν","pu":null,"pa":"Conj","st":"1437"},{"tl":"thelō","en":"I wish","gr":"θέλω","pu":",","pa":"V-PSA-1S","st":"2309"},{"tl":"didōmi","en":"I give","gr":"δίδωμι","pu":null,"pa":"V-PIA-1S","st":"1325"},{"tl":"autēn","en":"it","gr":"αὐτήν","pu":".","pa":"PPro-AF3S","st":"846"}],"7":[{"tl":"sy","en":"You","gr":"σὺ","pu":null,"pa":"PPro-N2S","st":"4771"},{"tl":"oun","en":"therefore","gr":"οὖν","pu":",","pa":"Conj","st":"3767"},{"tl":"ean","en":"if","gr":"ἐὰν","pu":null,"pa":"Conj","st":"1437"},{"tl":"proskynēsēs","en":"You will worship","gr":"προσκυνήσῃς","pu":null,"pa":"V-ASA-2S","st":"4352"},{"tl":"enōpion","en":"before","gr":"ἐνώπιον","pu":null,"pa":"Prep","st":"1799"},{"tl":"emou","en":"me","gr":"ἐμοῦ","pu":",","pa":"PPro-G1S","st":"1473"},{"tl":"estai","en":"will be","gr":"ἔσται","pu":null,"pa":"V-FIM-3S","st":"1510"},{"tl":"sou","en":"Yours","gr":"σοῦ","pu":null,"pa":"PPro-G2S","st":"4771"},{"tl":"pasa","en":"all","gr":"πᾶσα","pu":".","pa":"Adj-NFS","st":"3956"}],"8":[{"tl":"Kai","en":"And","gr":"Καὶ","pu":null,"pa":"Conj","st":"2532"},{"tl":"apokritheis","en":"answering","gr":"ἀποκριθεὶς","pu":",","pa":"V-APP-NMS","st":"611"},{"tl":"ho","en":" - ","gr":"ὁ","pu":null,"pa":"Art-NMS","st":"3588"},{"tl":"Iēsous","en":"Jesus","gr":"Ἰησοῦς","pu":null,"pa":"N-NMS","st":"2424"},{"tl":"eipen","en":"said","gr":"εἶπεν","pu":null,"pa":"V-AIA-3S","st":"2036"},{"tl":"autō","en":"to him","gr":"αὐτῷ","pu":",","pa":"PPro-DM3S","st":"846"},{"tl":"Gegraptai","en":"It has been written","gr":"Γέγραπται","pu":":","pa":"V-RIM/P-3S","st":"1125"},{"tl":"Proskynēseis","en":"You shall worship","gr":"Προσκυνήσεις ⇔","pu":null,"pa":"V-FIA-2S","st":"4352"},{"tl":"Kyrion","en":"[the] Lord","gr":"«Κύριον","pu":null,"pa":"N-AMS","st":"2962"},{"tl":"ton","en":" - ","gr":"τὸν","pu":null,"pa":"Art-AMS","st":"3588"},{"tl":"Theon","en":"God","gr":"Θεόν","pu":null,"pa":"N-AMS","st":"2316"},{"tl":"sou","en":"of you","gr":"σου»","pu":",","pa":"PPro-G2S","st":"4771"},{"tl":"kai","en":"and","gr":"καὶ","pu":null,"pa":"Conj","st":"2532"},{"tl":"autō","en":"Him","gr":"αὐτῷ","pu":null,"pa":"PPro-DM3S","st":"846"},{"tl":"monō","en":"only","gr":"μόνῳ","pu":null,"pa":"Adj-DMS","st":"3441"},{"tl":"latreuseis","en":"you shall serve","gr":"λατρεύσεις","pu":".","pa":"V-FIA-2S","st":"3000"}],"9":[{"tl":"Ēgagen","en":"He led","gr":"Ἤγαγεν","pu":null,"pa":"V-AIA-3S","st":"71"},{"tl":"de","en":"also","gr":"δὲ","pu":null,"pa":"Conj","st":"1161"},{"tl":"auton","en":"Him","gr":"αὐτὸν","pu":null,"pa":"PPro-AM3S","st":"846"},{"tl":"eis","en":"to","gr":"εἰς","pu":null,"pa":"Prep","st":"1519"},{"tl":"Ierousalēm","en":"Jerusalem","gr":"Ἰερουσαλὴμ","pu":null,"pa":"N-AFS","st":"2419"},{"tl":"kai","en":"and","gr":"καὶ","pu":null,"pa":"Conj","st":"2532"},{"tl":"estēsen","en":"set","gr":"ἔστησεν","pu":null,"pa":"V-AIA-3S","st":"2476"},{"tl":"epi","en":"upon","gr":"ἐπὶ","pu":null,"pa":"Prep","st":"1909"},{"tl":"to","en":"the","gr":"τὸ","pu":null,"pa":"Art-ANS","st":"3588"},{"tl":"pterygion","en":"pinnacle","gr":"πτερύγιον","pu":null,"pa":"N-ANS","st":"4419"},{"tl":"tou","en":"of the","gr":"τοῦ","pu":null,"pa":"Art-GNS","st":"3588"},{"tl":"hierou","en":"temple","gr":"ἱεροῦ","pu":",","pa":"N-GNS","st":"2411"},{"tl":"kai","en":"and","gr":"καὶ","pu":null,"pa":"Conj","st":"2532"},{"tl":"eipen","en":"said","gr":"εἶπεν","pu":null,"pa":"V-AIA-3S","st":"2036"},{"tl":"autō","en":"to Him","gr":"αὐτῷ","pu":",","pa":"PPro-DM3S","st":"846"},{"tl":"Ei","en":"If","gr":"Εἰ","pu":null,"pa":"Conj","st":"1487"},{"tl":"Huios","en":"[the] Son","gr":"Υἱὸς","pu":null,"pa":"N-NMS","st":"5207"},{"tl":"ei","en":"You are","gr":"εἶ","pu":null,"pa":"V-PIA-2S","st":"1510"},{"tl":"tou","en":" - ","gr":"τοῦ","pu":null,"pa":"Art-GMS","st":"3588"},{"tl":"Theou","en":"of God","gr":"Θεοῦ","pu":",","pa":"N-GMS","st":"2316"},{"tl":"bale","en":"cast","gr":"βάλε","pu":null,"pa":"V-AMA-2S","st":"906"},{"tl":"seauton","en":"Yourself","gr":"σεαυτὸν","pu":null,"pa":"PPro-AM2S","st":"4572"},{"tl":"enteuthen","en":"from here","gr":"ἐντεῦθεν","pu":null,"pa":"Adv","st":"1782"},{"tl":"katō","en":"down","gr":"κάτω","pu":".","pa":"Adv","st":"2736"}],"10":[{"tl":"gegraptai","en":"It has been written","gr":"γέγραπται","pu":null,"pa":"V-RIM/P-3S","st":"1125"},{"tl":"gar","en":"for","gr":"γὰρ","pu":null,"pa":"Conj","st":"1063"},{"tl":"hoti","en":" - ","gr":"ὅτι","pu":":","pa":"Conj","st":"3754"},{"tl":"Tois","en":"To the","gr":"Τοῖς","pu":null,"pa":"Art-DMP","st":"3588"},{"tl":"angelois","en":"angels","gr":"ἀγγέλοις","pu":null,"pa":"N-DMP","st":"32"},{"tl":"autou","en":"of Him","gr":"αὐτοῦ","pu":null,"pa":"PPro-GM3S","st":"846"},{"tl":"enteleitai","en":"He will give orders","gr":"ἐντελεῖται","pu":null,"pa":"V-FIM-3S","st":"1781"},{"tl":"peri","en":"concerning","gr":"περὶ","pu":null,"pa":"Prep","st":"4012"},{"tl":"sou","en":"You","gr":"σοῦ","pu":",","pa":"PPro-G2S","st":"4771"},{"tl":"tou","en":" - ","gr":"τοῦ","pu":null,"pa":"Art-GNS","st":"3588"},{"tl":"diaphylaxai","en":"to guard","gr":"διαφυλάξαι","pu":null,"pa":"V-ANA","st":"1314"},{"tl":"se","en":"You","gr":"σε","pu":";","pa":"PPro-A2S","st":"4771"}],"11":[{"tl":"kai","en":"and","gr":"καὶ","pu":null,"pa":"Conj","st":"2532"},{"tl":"hoti","en":" - ","gr":"ὅτι","pu":null,"pa":"Conj","st":"3754"},{"tl":"epi","en":"in","gr":"ἐπὶ","pu":null,"pa":"Prep","st":"1909"},{"tl":"cheirōn","en":"[their] hands","gr":"χειρῶν","pu":null,"pa":"N-GFP","st":"5495"},{"tl":"arousin","en":"will they bear","gr":"ἀροῦσίν","pu":null,"pa":"V-FIA-3P","st":"142"},{"tl":"se","en":"You","gr":"σε","pu":",","pa":"PPro-A2S","st":"4771"},{"tl":"mē","en":"lest","gr":"μή‿","pu":null,"pa":"Adv","st":"3361"},{"tl":"pote","en":"ever","gr":"ποτε","pu":null,"pa":"Conj","st":"4219"},{"tl":"proskopsēs","en":"You strike","gr":"προσκόψῃς","pu":null,"pa":"V-ASA-2S","st":"4350"},{"tl":"pros","en":"against","gr":"πρὸς","pu":null,"pa":"Prep","st":"4314"},{"tl":"lithon","en":"a stone","gr":"λίθον","pu":null,"pa":"N-AMS","st":"3037"},{"tl":"ton","en":"the","gr":"τὸν","pu":null,"pa":"Art-AMS","st":"3588"},{"tl":"poda","en":"foot","gr":"πόδα","pu":null,"pa":"N-AMS","st":"4228"},{"tl":"sou","en":"of You","gr":"σου","pu":".","pa":"PPro-G2S","st":"4771"}],"12":[{"tl":"Kai","en":"And","gr":"Καὶ","pu":null,"pa":"Conj","st":"2532"},{"tl":"apokritheis","en":"answering","gr":"ἀποκριθεὶς","pu":",","pa":"V-APP-NMS","st":"611"},{"tl":"eipen","en":"said","gr":"εἶπεν","pu":null,"pa":"V-AIA-3S","st":"2036"},{"tl":"autō","en":"to him","gr":"αὐτῷ","pu":null,"pa":"PPro-DM3S","st":"846"},{"tl":"ho","en":" - ","gr":"ὁ","pu":null,"pa":"Art-NMS","st":"3588"},{"tl":"Iēsous","en":"Jesus","gr":"Ἰησοῦς","pu":null,"pa":"N-NMS","st":"2424"},{"tl":"hoti","en":" - ","gr":"ὅτι","pu":",","pa":"Conj","st":"3754"},{"tl":"Eirētai","en":"It has been said","gr":"Εἴρηται","pu":",","pa":"V-RIM/P-3S","st":"2046"},{"tl":"Ouk","en":"Not","gr":"Οὐκ","pu":null,"pa":"Adv","st":"3756"},{"tl":"ekpeiraseis","en":"you shall test","gr":"ἐκπειράσεις","pu":null,"pa":"V-FIA-2S","st":"1598"},{"tl":"Kyrion","en":"[the] Lord","gr":"Κύριον","pu":null,"pa":"N-AMS","st":"2962"},{"tl":"ton","en":"the","gr":"τὸν","pu":null,"pa":"Art-AMS","st":"3588"},{"tl":"Theon","en":"God","gr":"Θεόν","pu":null,"pa":"N-AMS","st":"2316"},{"tl":"sou","en":"of you","gr":"σου","pu":".","pa":"PPro-G2S","st":"4771"}],"13":[{"tl":"Kai","en":"And","gr":"Καὶ","pu":null,"pa":"Conj","st":"2532"},{"tl":"syntelesas","en":"having finished","gr":"συντελέσας","pu":null,"pa":"V-APA-NMS","st":"4931"},{"tl":"panta","en":"every","gr":"πάντα","pu":null,"pa":"Adj-AMS","st":"3956"},{"tl":"peirasmon","en":"temptation","gr":"πειρασμὸν","pu":",","pa":"N-AMS","st":"3986"},{"tl":"ho","en":"the","gr":"ὁ","pu":null,"pa":"Art-NMS","st":"3588"},{"tl":"diabolos","en":"devil","gr":"διάβολος","pu":null,"pa":"Adj-NMS","st":"1228"},{"tl":"apestē","en":"departed","gr":"ἀπέστη","pu":null,"pa":"V-AIA-3S","st":"868"},{"tl":"ap’","en":"from","gr":"ἀπ’","pu":null,"pa":"Prep","st":"575"},{"tl":"autou","en":"Him","gr":"αὐτοῦ","pu":null,"pa":"PPro-GM3S","st":"846"},{"tl":"achri","en":"until","gr":"ἄχρι","pu":null,"pa":"Prep","st":"891"},{"tl":"kairou","en":"an opportune time","gr":"καιροῦ","pu":".","pa":"N-GMS","st":"2540"}],"14":[{"tl":"Kai","en":"And","gr":"Καὶ","pu":null,"pa":"Conj","st":"2532"},{"tl":"hypestrepsen","en":"returned","gr":"ὑπέστρεψεν","pu":null,"pa":"V-AIA-3S","st":"5290"},{"tl":"ho","en":" - ","gr":"ὁ","pu":null,"pa":"Art-NMS","st":"3588"},{"tl":"Iēsous","en":"Jesus","gr":"Ἰησοῦς","pu":null,"pa":"N-NMS","st":"2424"},{"tl":"en","en":"in","gr":"ἐν","pu":null,"pa":"Prep","st":"1722"},{"tl":"tē","en":"the","gr":"τῇ","pu":null,"pa":"Art-DFS","st":"3588"},{"tl":"dynamei","en":"power","gr":"δυνάμει","pu":null,"pa":"N-DFS","st":"1411"},{"tl":"tou","en":"of the","gr":"τοῦ","pu":null,"pa":"Art-GNS","st":"3588"},{"tl":"Pneumatos","en":"Spirit","gr":"Πνεύματος","pu":null,"pa":"N-GNS","st":"4151"},{"tl":"eis","en":"to","gr":"εἰς","pu":null,"pa":"Prep","st":"1519"},{"tl":"tēn","en":" - ","gr":"τὴν","pu":null,"pa":"Art-AFS","st":"3588"},{"tl":"Galilaian","en":"Galilee","gr":"Γαλιλαίαν","pu":";","pa":"N-AFS","st":"1056"},{"tl":"kai","en":"and","gr":"καὶ","pu":null,"pa":"Conj","st":"2532"},{"tl":"phēmē","en":"a report","gr":"φήμη","pu":null,"pa":"N-NFS","st":"5345"},{"tl":"exēlthen","en":"went out","gr":"ἐξῆλθεν","pu":null,"pa":"V-AIA-3S","st":"1831"},{"tl":"kath’","en":"into","gr":"καθ’","pu":null,"pa":"Prep","st":"2596"},{"tl":"holēs","en":"all","gr":"ὅλης","pu":null,"pa":"Adj-GFS","st":"3650"},{"tl":"tēs","en":"the","gr":"τῆς","pu":null,"pa":"Art-GFS","st":"3588"},{"tl":"perichōrou","en":"surrounding region","gr":"περιχώρου","pu":null,"pa":"Adj-GFS","st":"4066"},{"tl":"peri","en":"concerning","gr":"περὶ","pu":null,"pa":"Prep","st":"4012"},{"tl":"autou","en":"Him","gr":"αὐτοῦ","pu":".","pa":"PPro-GM3S","st":"846"}],"15":[{"tl":"kai","en":"And","gr":"καὶ","pu":null,"pa":"Conj","st":"2532"},{"tl":"autos","en":"He","gr":"αὐτὸς","pu":null,"pa":"PPro-NM3S","st":"846"},{"tl":"edidasken","en":"was teaching","gr":"ἐδίδασκεν","pu":null,"pa":"V-IIA-3S","st":"1321"},{"tl":"en","en":"in","gr":"ἐν","pu":null,"pa":"Prep","st":"1722"},{"tl":"tais","en":"the","gr":"ταῖς","pu":null,"pa":"Art-DFP","st":"3588"},{"tl":"synagōgais","en":"synagogues","gr":"συναγωγαῖς","pu":null,"pa":"N-DFP","st":"4864"},{"tl":"autōn","en":"of them","gr":"αὐτῶν","pu":",","pa":"PPro-GM3P","st":"846"},{"tl":"doxazomenos","en":"being glorified","gr":"δοξαζόμενος","pu":null,"pa":"V-PPM/P-NMS","st":"1392"},{"tl":"hypo","en":"by","gr":"ὑπὸ","pu":null,"pa":"Prep","st":"5259"},{"tl":"pantōn","en":"all","gr":"πάντων","pu":".","pa":"Adj-GMP","st":"3956"}],"16":[{"tl":"Kai","en":"And","gr":"Καὶ","pu":null,"pa":"Conj","st":"2532"},{"tl":"ēlthen","en":"He came","gr":"ἦλθεν","pu":null,"pa":"V-AIA-3S","st":"2064"},{"tl":"eis","en":"to","gr":"εἰς","pu":null,"pa":"Prep","st":"1519"},{"tl":"Nazara","en":"Nazareth","gr":"Ναζαρά","pu":",","pa":"N-AFS","st":"3478"},{"tl":"hou","en":"where","gr":"οὗ","pu":null,"pa":"Adv","st":"3757"},{"tl":"ēn","en":"He had been","gr":"ἦν","pu":null,"pa":"V-IIA-3S","st":"1510"},{"tl":"tethrammenos","en":"brought up","gr":"τεθραμμένος","pu":";","pa":"V-RPM/P-NMS","st":"5142"},{"tl":"kai","en":"and","gr":"καὶ","pu":null,"pa":"Conj","st":"2532"},{"tl":"eisēlthen","en":"He entered","gr":"εἰσῆλθεν","pu":null,"pa":"V-AIA-3S","st":"1525"},{"tl":"kata","en":"according to","gr":"κατὰ","pu":null,"pa":"Prep","st":"2596"},{"tl":"to","en":"the","gr":"τὸ","pu":null,"pa":"Art-ANS","st":"3588"},{"tl":"eiōthos","en":"custom","gr":"εἰωθὸς","pu":null,"pa":"V-RPA-ANS","st":"1486"},{"tl":"autō","en":"to Him","gr":"αὐτῷ","pu":",","pa":"PPro-DM3S","st":"846"},{"tl":"en","en":"on","gr":"ἐν","pu":null,"pa":"Prep","st":"1722"},{"tl":"tē","en":"the","gr":"τῇ","pu":null,"pa":"Art-DFS","st":"3588"},{"tl":"hēmera","en":"day","gr":"ἡμέρᾳ","pu":null,"pa":"N-DFS","st":"2250"},{"tl":"tōn","en":"of the","gr":"τῶν","pu":null,"pa":"Art-GNP","st":"3588"},{"tl":"sabbatōn","en":"Sabbaths","gr":"σαββάτων","pu":",","pa":"N-GNP","st":"4521"},{"tl":"eis","en":"into","gr":"εἰς","pu":null,"pa":"Prep","st":"1519"},{"tl":"tēn","en":"the","gr":"τὴν","pu":null,"pa":"Art-AFS","st":"3588"},{"tl":"synagōgēn","en":"synagogue","gr":"συναγωγήν","pu":",","pa":"N-AFS","st":"4864"},{"tl":"kai","en":"and","gr":"καὶ","pu":null,"pa":"Conj","st":"2532"},{"tl":"anestē","en":"stood up","gr":"ἀνέστη","pu":null,"pa":"V-AIA-3S","st":"450"},{"tl":"anagnōnai","en":"to read","gr":"ἀναγνῶναι","pu":".","pa":"V-ANA","st":"314"}],"17":[{"tl":"kai","en":"And","gr":"καὶ","pu":null,"pa":"Conj","st":"2532"},{"tl":"epedothē","en":"there was given","gr":"ἐπεδόθη","pu":null,"pa":"V-AIP-3S","st":"1929"},{"tl":"autō","en":"to Him","gr":"αὐτῷ","pu":null,"pa":"PPro-DM3S","st":"846"},{"tl":"biblion","en":"[the] scroll of","gr":"βιβλίον","pu":null,"pa":"N-NNS","st":"975"},{"tl":"tou","en":"the","gr":"τοῦ","pu":null,"pa":"Art-GMS","st":"3588"},{"tl":"prophētou","en":"prophet","gr":"προφήτου","pu":null,"pa":"N-GMS","st":"4396"},{"tl":"Ēsaiou","en":"Isaiah","gr":"Ἠσαΐου","pu":",","pa":"N-GMS","st":"2268"},{"tl":"kai","en":"and","gr":"καὶ","pu":null,"pa":"Conj","st":"2532"},{"tl":"anaptyxas","en":"having unrolled","gr":"ἀναπτύξας*","pu":null,"pa":"V-APA-NMS","st":"380"},{"tl":"to","en":"the","gr":"τὸ","pu":null,"pa":"Art-ANS","st":"3588"},{"tl":"biblion","en":"scroll","gr":"βιβλίον","pu":",","pa":"N-ANS","st":"975"},{"tl":"heuren","en":"He found","gr":"εὗρεν","pu":null,"pa":"V-AIA-3S","st":"2147"},{"tl":"ton","en":"the","gr":"τὸν","pu":null,"pa":"Art-AMS","st":"3588"},{"tl":"topon","en":"place","gr":"τόπον","pu":null,"pa":"N-AMS","st":"5117"},{"tl":"hou","en":"where","gr":"οὗ","pu":null,"pa":"Adv","st":"3739"},{"tl":"ēn","en":"it was","gr":"ἦν","pu":null,"pa":"V-IIA-3S","st":"1510"},{"tl":"gegrammenon","en":"written","gr":"γεγραμμένον","pu":":","pa":"V-RPM/P-NNS","st":"1125"}],"18":[{"tl":"Pneuma","en":"[The] Spirit","gr":"Πνεῦμα","pu":null,"pa":"N-NNS","st":"4151"},{"tl":"Kyriou","en":"of [the] Lord [is]","gr":"Κυρίου","pu":null,"pa":"N-GMS","st":"2962"},{"tl":"ep’","en":"upon","gr":"ἐπ’","pu":null,"pa":"Prep","st":"1909"},{"tl":"eme","en":"Me","gr":"ἐμέ","pu":",","pa":"PPro-A1S","st":"1473"},{"tl":"Hou","en":"of which","gr":"Οὗ","pu":null,"pa":"RelPro-GNS","st":"3739"},{"tl":"heineken","en":"because","gr":"εἵνεκεν","pu":null,"pa":"Prep","st":"1752"},{"tl":"echrisen","en":"He has anointed","gr":"ἔχρισέν","pu":null,"pa":"V-AIA-3S","st":"5548"},{"tl":"me","en":"Me","gr":"με","pu":null,"pa":"PPro-A1S","st":"1473"},{"tl":"Euangelisasthai","en":"to preach good news","gr":"Εὐαγγελίσασθαι","pu":null,"pa":"V-ANM","st":"2097"},{"tl":"ptōchois","en":"to [the] poor","gr":"πτωχοῖς","pu":".","pa":"Adj-DMP","st":"4434"},{"tl":"Apestalken","en":"He has sent","gr":"Ἀπέσταλκέν","pu":null,"pa":"V-RIA-3S","st":"649"},{"tl":"me","en":"Me","gr":"με","pu":null,"pa":"PPro-A1S","st":"1473"},{"tl":"iasasthai","en":"to heal","gr":"⧼ἰάσασθαι","pu":null,"pa":"V-ANM-3S","st":"2390"},{"tl":"tous","en":"the","gr":"τοὺς","pu":null,"pa":"Art-AMP","st":"3588"},{"tl":"syntetrimmenous","en":"broken","gr":"συντετριμμένους","pu":null,"pa":"V-RPP-AMP","st":"4937"},{"tl":"tēn","en":" - ","gr":"τὴν","pu":null,"pa":"Art-AFS","st":"3588"},{"tl":"kardian","en":"in heart","gr":"καρδίαν⧽","pu":",","pa":"N-AFS","st":"2588"},{"tl":"kēryxai","en":"to proclaim","gr":"κηρῦξαι","pu":null,"pa":"V-ANA","st":"2784"},{"tl":"aichmalōtois","en":"to [the] captives","gr":"αἰχμαλώτοις","pu":null,"pa":"N-DMP","st":"164"},{"tl":"aphesin","en":"deliverance","gr":"ἄφεσιν","pu":",","pa":"N-AFS","st":"859"},{"tl":"Kai","en":"and","gr":"Καὶ","pu":null,"pa":"Conj","st":"2532"},{"tl":"typhlois","en":"to [the] blind","gr":"τυφλοῖς","pu":null,"pa":"Adj-DMP","st":"5185"},{"tl":"anablepsin","en":"recovery of sight","gr":"ἀνάβλεψιν","pu":",","pa":"N-AFS","st":"309"},{"tl":"Aposteilai","en":"to send forth","gr":"Ἀποστεῖλαι","pu":null,"pa":"V-ANA","st":"649"},{"tl":"tethrausmenous","en":"[the] oppressed","gr":"τεθραυσμένους","pu":null,"pa":"V-RPM/P-AMP","st":"2352"},{"tl":"en","en":"in","gr":"ἐν","pu":null,"pa":"Prep","st":"1722"},{"tl":"aphesei","en":"deliverance","gr":"ἀφέσει","pu":",","pa":"N-DFS","st":"859"}],"19":[{"tl":"Kēryxai","en":"to proclaim","gr":"Κηρῦξαι","pu":null,"pa":"V-ANA","st":"2784"},{"tl":"eniauton","en":"[the] year","gr":"ἐνιαυτὸν","pu":null,"pa":"N-AMS","st":"1763"},{"tl":"Kyriou","en":"of [the] Lord’s","gr":"Κυρίου","pu":null,"pa":"N-GMS","st":"2962"},{"tl":"dekton","en":"favor","gr":"δεκτόν","pu":".","pa":"Adj-AMS","st":"1184"}],"20":[{"tl":"Kai","en":"And","gr":"Καὶ","pu":null,"pa":"Conj","st":"2532"},{"tl":"ptyxas","en":"having rolled up","gr":"πτύξας","pu":null,"pa":"V-APA-NMS","st":"4428"},{"tl":"to","en":"the","gr":"τὸ","pu":null,"pa":"Art-ANS","st":"3588"},{"tl":"biblion","en":"scroll","gr":"βιβλίον","pu":",","pa":"N-ANS","st":"975"},{"tl":"apodous","en":"having delivered [it]","gr":"ἀποδοὺς","pu":null,"pa":"V-APA-NMS","st":"591"},{"tl":"tō","en":"to the","gr":"τῷ","pu":null,"pa":"Art-DMS","st":"3588"},{"tl":"hypēretē","en":"attendant","gr":"ὑπηρέτῃ","pu":",","pa":"N-DMS","st":"5257"},{"tl":"ekathisen","en":"He sat down","gr":"ἐκάθισεν","pu":",","pa":"V-AIA-3S","st":"2523"},{"tl":"kai","en":"and","gr":"καὶ","pu":null,"pa":"Conj","st":"2532"},{"tl":"pantōn","en":"of all","gr":"πάντων","pu":null,"pa":"Adj-GMP","st":"3956"},{"tl":"hoi","en":"the","gr":"οἱ","pu":null,"pa":"Art-NMP","st":"3588"},{"tl":"ophthalmoi","en":"eyes","gr":"ὀφθαλμοὶ","pu":null,"pa":"N-NMP","st":"3788"},{"tl":"en","en":"in","gr":"ἐν","pu":null,"pa":"Prep","st":"1722"},{"tl":"tē","en":"the","gr":"τῇ","pu":null,"pa":"Art-DFS","st":"3588"},{"tl":"synagōgē","en":"synagogue","gr":"συναγωγῇ","pu":null,"pa":"N-DFS","st":"4864"},{"tl":"ēsan","en":"were","gr":"ἦσαν","pu":null,"pa":"V-IIA-3P","st":"1510"},{"tl":"atenizontes","en":"fixed upon","gr":"ἀτενίζοντες","pu":null,"pa":"V-PPA-NMP","st":"816"},{"tl":"autō","en":"Him","gr":"αὐτῷ","pu":".","pa":"PPro-DM3S","st":"846"}],"21":[{"tl":"ērxato","en":"He began","gr":"ἤρξατο","pu":null,"pa":"V-AIM-3S","st":"756"},{"tl":"de","en":"then","gr":"δὲ","pu":null,"pa":"Conj","st":"1161"},{"tl":"legein","en":"to say","gr":"λέγειν","pu":null,"pa":"V-PNA","st":"3004"},{"tl":"pros","en":"to","gr":"πρὸς","pu":null,"pa":"Prep","st":"4314"},{"tl":"autous","en":"them","gr":"αὐτοὺς","pu":null,"pa":"PPro-AM3P","st":"846"},{"tl":"hoti","en":" - ","gr":"ὅτι","pu":",","pa":"Conj","st":"3754"},{"tl":"Sēmeron","en":"Today","gr":"Σήμερον","pu":null,"pa":"Adv","st":"4594"},{"tl":"peplērōtai","en":"is fulfilled","gr":"πεπλήρωται","pu":null,"pa":"V-RIM/P-3S","st":"4137"},{"tl":"hē","en":"the","gr":"ἡ","pu":null,"pa":"Art-NFS","st":"3588"},{"tl":"graphē","en":"Scripture","gr":"γραφὴ","pu":null,"pa":"N-NFS","st":"1124"},{"tl":"hautē","en":"this","gr":"αὕτη","pu":",","pa":"DPro-NFS","st":"3778"},{"tl":"en","en":"in","gr":"ἐν","pu":null,"pa":"Prep","st":"1722"},{"tl":"tois","en":"the","gr":"τοῖς","pu":null,"pa":"Art-DNP","st":"3588"},{"tl":"ōsin","en":"hearing","gr":"ὠσὶν","pu":null,"pa":"N-DNP","st":"3775"},{"tl":"hymōn","en":"of you","gr":"ὑμῶν","pu":".","pa":"PPro-G2P","st":"4771"}],"22":[{"tl":"Kai","en":"And","gr":"Καὶ","pu":null,"pa":"Conj","st":"2532"},{"tl":"pantes","en":"all","gr":"πάντες","pu":null,"pa":"Adj-NMP","st":"3956"},{"tl":"emartyroun","en":"were bearing witness","gr":"ἐμαρτύρουν","pu":null,"pa":"V-IIA-3P","st":"3140"},{"tl":"autō","en":"to Him","gr":"αὐτῷ","pu":null,"pa":"PPro-DM3S","st":"846"},{"tl":"kai","en":"and","gr":"καὶ","pu":null,"pa":"Conj","st":"2532"},{"tl":"ethaumazon","en":"marveling","gr":"ἐθαύμαζον","pu":null,"pa":"V-IIA-3P","st":"2296"},{"tl":"epi","en":"at","gr":"ἐπὶ","pu":null,"pa":"Prep","st":"1909"},{"tl":"tois","en":"the","gr":"τοῖς","pu":null,"pa":"Art-DMP","st":"3588"},{"tl":"logois","en":"words","gr":"λόγοις","pu":null,"pa":"N-DMP","st":"3056"},{"tl":"tēs","en":"of the","gr":"τῆς","pu":null,"pa":"Art-GFS","st":"3588"},{"tl":"charitos","en":"grace","gr":"χάριτος","pu":null,"pa":"N-GFS","st":"5485"},{"tl":"tois","en":"that","gr":"τοῖς","pu":null,"pa":"Art-DMP","st":"3588"},{"tl":"ekporeuomenois","en":"are proceeding","gr":"ἐκπορευομένοις","pu":null,"pa":"V-PPM/P-DMP","st":"1607"},{"tl":"ek","en":"out of","gr":"ἐκ","pu":null,"pa":"Prep","st":"1537"},{"tl":"tou","en":"the","gr":"τοῦ","pu":null,"pa":"Art-GNS","st":"3588"},{"tl":"stomatos","en":"mouth","gr":"στόματος","pu":null,"pa":"N-GNS","st":"4750"},{"tl":"autou","en":"of Him","gr":"αὐτοῦ","pu":";","pa":"PPro-GM3S","st":"846"},{"tl":"kai","en":"and","gr":"καὶ","pu":null,"pa":"Conj","st":"2532"},{"tl":"elegon","en":"they were saying","gr":"ἔλεγον","pu":",","pa":"V-IIA-3P","st":"2036"},{"tl":"Ouchi","en":"Not","gr":"Οὐχὶ","pu":null,"pa":"IntPrtcl","st":"3780"},{"tl":"huios","en":"the son","gr":"υἱός","pu":null,"pa":"N-NMS","st":"5207"},{"tl":"estin","en":"is","gr":"ἐστιν","pu":null,"pa":"V-PIA-3S","st":"1510"},{"tl":"Iōsēph","en":"of Joseph","gr":"Ἰωσὴφ","pu":null,"pa":"N-GMS","st":"2501"},{"tl":"houtos","en":"this","gr":"οὗτος","pu":"?","pa":"DPro-NMS","st":"3778"}],"23":[{"tl":"Kai","en":"And","gr":"Καὶ","pu":null,"pa":"Conj","st":"2532"},{"tl":"eipen","en":"He said","gr":"εἶπεν","pu":null,"pa":"V-AIA-3S","st":"2036"},{"tl":"pros","en":"to","gr":"πρὸς","pu":null,"pa":"Prep","st":"4314"},{"tl":"autous","en":"them","gr":"αὐτούς","pu":",","pa":"PPro-AM3P","st":"846"},{"tl":"Pantōs","en":"Surely","gr":"Πάντως","pu":null,"pa":"Adv","st":"3843"},{"tl":"ereite","en":"you will say","gr":"ἐρεῖτέ","pu":null,"pa":"V-FIA-2P","st":"2046"},{"tl":"moi","en":"to Me","gr":"μοι","pu":null,"pa":"PPro-D1S","st":"1473"},{"tl":"tēn","en":"the","gr":"τὴν","pu":null,"pa":"Art-AFS","st":"3588"},{"tl":"parabolēn","en":"proverb","gr":"παραβολὴν","pu":null,"pa":"N-AFS","st":"3850"},{"tl":"tautēn","en":"this","gr":"ταύτην","pu":",","pa":"DPro-AFS","st":"3778"},{"tl":"Iatre","en":"Physician","gr":"Ἰατρέ","pu":null,"pa":"N-VMS","st":"2395"},{"tl":"therapeuson","en":"heal","gr":"θεράπευσον","pu":null,"pa":"V-AMA-2S","st":"2323"},{"tl":"seauton","en":"yourself","gr":"σεαυτόν","pu":"!","pa":"PPro-AM2S","st":"4572"},{"tl":"hosa","en":"Whatsoever","gr":"ὅσα","pu":null,"pa":"RelPro-ANP","st":"3745"},{"tl":"ēkousamen","en":"we have heard","gr":"ἠκούσαμεν","pu":null,"pa":"V-AIA-1P","st":"191"},{"tl":"genomena","en":"has been done","gr":"γενόμενα","pu":null,"pa":"V-APM-ANP","st":"1096"},{"tl":"eis","en":"in","gr":"εἰς","pu":null,"pa":"Prep","st":"1519"},{"tl":"tēn","en":" - ","gr":"τὴν","pu":null,"pa":"Art-AFS","st":"3588"},{"tl":"Kapharnaoum","en":"Capernaum","gr":"Καφαρναοὺμ","pu":",","pa":"N-AFS","st":"2584"},{"tl":"poiēson","en":"do","gr":"ποίησον","pu":null,"pa":"V-AMA-2S","st":"4160"},{"tl":"kai","en":"also","gr":"καὶ","pu":null,"pa":"Conj","st":"2532"},{"tl":"hōde","en":"here","gr":"ὧδε","pu":null,"pa":"Adv","st":"5602"},{"tl":"en","en":"in","gr":"ἐν","pu":null,"pa":"Prep","st":"1722"},{"tl":"tē","en":"the","gr":"τῇ","pu":null,"pa":"Art-DFS","st":"3588"},{"tl":"patridi","en":"hometown","gr":"πατρίδι","pu":null,"pa":"N-DFS","st":"3968"},{"tl":"sou","en":"of You","gr":"σου","pu":".","pa":"PPro-G2S","st":"4771"}],"24":[{"tl":"Eipen","en":"He said","gr":"Εἶπεν","pu":null,"pa":"V-AIA-3S","st":"2036"},{"tl":"de","en":"then","gr":"δέ","pu":",","pa":"Conj","st":"1161"},{"tl":"Amēn","en":"Truly","gr":"Ἀμὴν","pu":null,"pa":"Heb","st":"281"},{"tl":"legō","en":"I say","gr":"λέγω","pu":null,"pa":"V-PIA-1S","st":"3004"},{"tl":"hymin","en":"to you","gr":"ὑμῖν","pu":null,"pa":"PPro-D2P","st":"4771"},{"tl":"hoti","en":"that","gr":"ὅτι","pu":null,"pa":"Conj","st":"3754"},{"tl":"oudeis","en":"no","gr":"οὐδεὶς","pu":null,"pa":"Adj-NMS","st":"3762"},{"tl":"prophētēs","en":"prophet","gr":"προφήτης","pu":null,"pa":"N-NMS","st":"4396"},{"tl":"dektos","en":"acceptable","gr":"δεκτός","pu":null,"pa":"Adj-NMS","st":"1184"},{"tl":"estin","en":"is","gr":"ἐστιν","pu":null,"pa":"V-PIA-3S","st":"1510"},{"tl":"en","en":"in","gr":"ἐν","pu":null,"pa":"Prep","st":"1722"},{"tl":"tē","en":"the","gr":"τῇ","pu":null,"pa":"Art-DFS","st":"3588"},{"tl":"patridi","en":"hometown","gr":"πατρίδι","pu":null,"pa":"N-DFS","st":"3968"},{"tl":"autou","en":"of him","gr":"αὐτοῦ","pu":".","pa":"PPro-GM3S","st":"846"}],"25":[{"tl":"ep’","en":"In","gr":"ἐπ’","pu":null,"pa":"Prep","st":"1909"},{"tl":"alētheias","en":"truth","gr":"ἀληθείας","pu":null,"pa":"N-GFS","st":"225"},{"tl":"de","en":"now","gr":"δὲ","pu":null,"pa":"Conj","st":"1161"},{"tl":"legō","en":"I say","gr":"λέγω","pu":null,"pa":"V-PIA-1S","st":"3004"},{"tl":"hymin","en":"to you","gr":"ὑμῖν","pu":",","pa":"PPro-D2P","st":"4771"},{"tl":"pollai","en":"many","gr":"πολλαὶ","pu":null,"pa":"Adj-NFP","st":"4183"},{"tl":"chērai","en":"widows","gr":"χῆραι","pu":null,"pa":"N-NFP","st":"5503"},{"tl":"ēsan","en":"there were","gr":"ἦσαν","pu":null,"pa":"V-IIA-3P","st":"1510"},{"tl":"en","en":"in","gr":"ἐν","pu":null,"pa":"Prep","st":"1722"},{"tl":"tais","en":"the","gr":"ταῖς","pu":null,"pa":"Art-DFP","st":"3588"},{"tl":"hēmerais","en":"days","gr":"ἡμέραις","pu":null,"pa":"N-DFP","st":"2250"},{"tl":"Ēliou","en":"of Elijah","gr":"Ἠλίου","pu":null,"pa":"N-GMS","st":"2243"},{"tl":"en","en":"in","gr":"ἐν","pu":null,"pa":"Prep","st":"1722"},{"tl":"tō","en":" - ","gr":"τῷ","pu":null,"pa":"Art-DMS","st":"3588"},{"tl":"Israēl","en":"Israel","gr":"Ἰσραήλ","pu":",","pa":"N-DMS","st":"2474"},{"tl":"hote","en":"when","gr":"ὅτε","pu":null,"pa":"Adv","st":"3753"},{"tl":"ekleisthē","en":"was shut up","gr":"ἐκλείσθη","pu":null,"pa":"V-AIP-3S","st":"2808"},{"tl":"ho","en":"the","gr":"ὁ","pu":null,"pa":"Art-NMS","st":"3588"},{"tl":"ouranos","en":"heaven","gr":"οὐρανὸς","pu":null,"pa":"N-NMS","st":"3772"},{"tl":"epi","en":"for","gr":"ἐπὶ","pu":null,"pa":"Prep","st":"1909"},{"tl":"etē","en":"years","gr":"ἔτη","pu":null,"pa":"N-ANP","st":"2094"},{"tl":"tria","en":"three","gr":"τρία","pu":null,"pa":"Adj-ANP","st":"5140"},{"tl":"kai","en":"and","gr":"καὶ","pu":null,"pa":"Conj","st":"2532"},{"tl":"mēnas","en":"months","gr":"μῆνας","pu":null,"pa":"N-AMP","st":"3376"},{"tl":"hex","en":"six","gr":"ἕξ","pu":",","pa":"Adj-AMP","st":"1803"},{"tl":"hōs","en":"when","gr":"ὡς","pu":null,"pa":"Adv","st":"5613"},{"tl":"egeneto","en":"there was","gr":"ἐγένετο","pu":null,"pa":"V-AIM-3S","st":"1096"},{"tl":"limos","en":"a famine","gr":"λιμὸς","pu":null,"pa":"N-NMS","st":"3042"},{"tl":"megas","en":"great","gr":"μέγας","pu":null,"pa":"Adj-NMS","st":"3173"},{"tl":"epi","en":"upon","gr":"ἐπὶ","pu":null,"pa":"Prep","st":"1909"},{"tl":"pasan","en":"all","gr":"πᾶσαν","pu":null,"pa":"Adj-AFS","st":"3956"},{"tl":"tēn","en":"the","gr":"τὴν","pu":null,"pa":"Art-AFS","st":"3588"},{"tl":"gēn","en":"land","gr":"γῆν","pu":";","pa":"N-AFS","st":"1093"}],"26":[{"tl":"kai","en":"and","gr":"καὶ","pu":null,"pa":"Conj","st":"2532"},{"tl":"pros","en":"to","gr":"πρὸς","pu":null,"pa":"Prep","st":"4314"},{"tl":"oudemian","en":"none","gr":"οὐδεμίαν","pu":null,"pa":"Adj-AFS","st":"3762"},{"tl":"autōn","en":"of them","gr":"αὐτῶν","pu":null,"pa":"PPro-GF3P","st":"846"},{"tl":"epemphthē","en":"was sent","gr":"ἐπέμφθη","pu":null,"pa":"V-AIP-3S","st":"3992"},{"tl":"Ēlias","en":"Elijah","gr":"Ἠλίας","pu":",","pa":"N-NMS","st":"2243"},{"tl":"ei","en":"if","gr":"εἰ","pu":null,"pa":"Conj","st":"1487"},{"tl":"mē","en":"not","gr":"μὴ","pu":null,"pa":"Adv","st":"3361"},{"tl":"eis","en":"to","gr":"εἰς","pu":null,"pa":"Prep","st":"1519"},{"tl":"Sarepta","en":"Zarephath","gr":"Σάρεπτα","pu":null,"pa":"N-ANP","st":"4558"},{"tl":"tēs","en":" - ","gr":"τῆς","pu":null,"pa":"Art-GFS","st":"3588"},{"tl":"Sidōnias","en":"of Sidon","gr":"Σιδωνίας","pu":",","pa":"N-GFS","st":"4606"},{"tl":"pros","en":"to","gr":"πρὸς","pu":null,"pa":"Prep","st":"4314"},{"tl":"gynaika","en":"a woman","gr":"γυναῖκα","pu":",","pa":"N-AFS","st":"1135"},{"tl":"chēran","en":"a widow","gr":"χήραν","pu":".","pa":"Adj-AFS","st":"5503"}],"27":[{"tl":"kai","en":"And","gr":"καὶ","pu":null,"pa":"Conj","st":"2532"},{"tl":"polloi","en":"many","gr":"πολλοὶ","pu":null,"pa":"Adj-NMP","st":"4183"},{"tl":"leproi","en":"lepers","gr":"λεπροὶ","pu":null,"pa":"Adj-NMP","st":"3015"},{"tl":"ēsan","en":"were","gr":"ἦσαν","pu":null,"pa":"V-IIA-3P","st":"1510"},{"tl":"en","en":"in","gr":"ἐν","pu":null,"pa":"Prep","st":"1722"},{"tl":"tō","en":" - ","gr":"τῷ","pu":null,"pa":"Art-DMS","st":"3588"},{"tl":"Israēl","en":"Israel","gr":"Ἰσραὴλ","pu":null,"pa":"N-DMS","st":"2474"},{"tl":"epi","en":"in the time","gr":"ἐπὶ","pu":null,"pa":"Prep","st":"1909"},{"tl":"Elisaiou","en":"of Elisha","gr":"Ἐλισαίου","pu":null,"pa":"N-GMS","st":"1666"},{"tl":"tou","en":"the","gr":"τοῦ","pu":null,"pa":"Art-GMS","st":"3588"},{"tl":"prophētou","en":"prophet","gr":"προφήτου","pu":",","pa":"N-GMS","st":"4396"},{"tl":"kai","en":"and","gr":"καὶ","pu":null,"pa":"Conj","st":"2532"},{"tl":"oudeis","en":"none","gr":"οὐδεὶς","pu":null,"pa":"Adj-NMS","st":"3762"},{"tl":"autōn","en":"of them","gr":"αὐτῶν","pu":null,"pa":"PPro-GM3P","st":"846"},{"tl":"ekatharisthē","en":"was cleansed","gr":"ἐκαθαρίσθη","pu":",","pa":"V-AIP-3S","st":"2511"},{"tl":"ei","en":"if","gr":"εἰ","pu":null,"pa":"Conj","st":"1487"},{"tl":"mē","en":"not","gr":"μὴ","pu":null,"pa":"Adv","st":"3361"},{"tl":"Naiman","en":"Naaman","gr":"Ναιμὰν","pu":null,"pa":"N-NMS","st":"3497"},{"tl":"ho","en":"the","gr":"ὁ","pu":null,"pa":"Art-NMS","st":"3588"},{"tl":"Syros","en":"Syrian","gr":"Σύρος","pu":".","pa":"N-NMS","st":"4948"}],"28":[{"tl":"Kai","en":"And","gr":"Καὶ","pu":null,"pa":"Conj","st":"2532"},{"tl":"eplēsthēsan","en":"were filled","gr":"ἐπλήσθησαν","pu":null,"pa":"V-AIP-3P","st":"4130"},{"tl":"pantes","en":"all","gr":"πάντες","pu":null,"pa":"Adj-NMP","st":"3956"},{"tl":"thymou","en":"with anger","gr":"θυμοῦ","pu":null,"pa":"N-GMS","st":"2372"},{"tl":"en","en":"in","gr":"ἐν","pu":null,"pa":"Prep","st":"1722"},{"tl":"tē","en":"the","gr":"τῇ","pu":null,"pa":"Art-DFS","st":"3588"},{"tl":"synagōgē","en":"synagogue","gr":"συναγωγῇ","pu":",","pa":"N-DFS","st":"4864"},{"tl":"akouontes","en":"hearing","gr":"ἀκούοντες","pu":null,"pa":"V-PPA-NMP","st":"191"},{"tl":"tauta","en":"these things","gr":"ταῦτα","pu":";","pa":"DPro-ANP","st":"3778"}],"29":[{"tl":"kai","en":"and","gr":"καὶ","pu":null,"pa":"Conj","st":"2532"},{"tl":"anastantes","en":"having risen up","gr":"ἀναστάντες","pu":",","pa":"V-APA-NMP","st":"450"},{"tl":"exebalon","en":"they cast","gr":"ἐξέβαλον","pu":null,"pa":"V-AIA-3P","st":"1544"},{"tl":"auton","en":"Him","gr":"αὐτὸν","pu":null,"pa":"PPro-AM3S","st":"846"},{"tl":"exō","en":"out","gr":"ἔξω","pu":null,"pa":"Prep","st":"1854"},{"tl":"tēs","en":"of [the]","gr":"τῆς","pu":null,"pa":"Art-GFS","st":"3588"},{"tl":"poleōs","en":"city","gr":"πόλεως","pu":null,"pa":"N-GFS","st":"4172"},{"tl":"kai","en":"and","gr":"καὶ","pu":null,"pa":"Conj","st":"2532"},{"tl":"ēgagon","en":"led","gr":"ἤγαγον","pu":null,"pa":"V-AIA-3P","st":"71"},{"tl":"auton","en":"Him","gr":"αὐτὸν","pu":null,"pa":"PPro-AM3S","st":"846"},{"tl":"heōs","en":"unto","gr":"ἕως","pu":null,"pa":"Prep","st":"2193"},{"tl":"ophryos","en":"brow","gr":"ὀφρύος","pu":null,"pa":"N-GFS","st":"3790"},{"tl":"tou","en":"of the","gr":"τοῦ","pu":null,"pa":"Art-GNS","st":"3588"},{"tl":"orous","en":"hill","gr":"ὄρους","pu":null,"pa":"N-GNS","st":"3735"},{"tl":"eph’","en":"upon","gr":"ἐφ’","pu":null,"pa":"Prep","st":"1909"},{"tl":"hou","en":"which","gr":"οὗ","pu":null,"pa":"RelPro-GNS","st":"3739"},{"tl":"hē","en":"the","gr":"ἡ","pu":null,"pa":"Art-NFS","st":"3588"},{"tl":"polis","en":"town","gr":"πόλις","pu":null,"pa":"N-NFS","st":"4172"},{"tl":"ōkodomēto","en":"had been built","gr":"ᾠκοδόμητο","pu":null,"pa":"V-LIM/P-3S","st":"3618"},{"tl":"autōn","en":"of them","gr":"αὐτῶν","pu":",","pa":"PPro-GM3P","st":"846"},{"tl":"hōste","en":"in order","gr":"ὥστε","pu":null,"pa":"Conj","st":"5620"},{"tl":"katakrēmnisai","en":"to throw over","gr":"κατακρημνίσαι","pu":null,"pa":"V-ANA","st":"2630"},{"tl":"auton","en":"him","gr":"αὐτόν","pu":";","pa":"PPro-AM3S","st":"846"}],"30":[{"tl":"autos","en":"He","gr":"αὐτὸς","pu":null,"pa":"PPro-NM3S","st":"846"},{"tl":"de","en":"however","gr":"δὲ","pu":",","pa":"Conj","st":"1161"},{"tl":"dielthōn","en":"having passed","gr":"διελθὼν","pu":null,"pa":"V-APA-NMS","st":"1330"},{"tl":"dia","en":"through","gr":"διὰ","pu":null,"pa":"Prep","st":"1223"},{"tl":"mesou","en":"[the] midst","gr":"μέσου","pu":null,"pa":"Adj-GNS","st":"3319"},{"tl":"autōn","en":"of them","gr":"αὐτῶν","pu":",","pa":"PPro-GM3P","st":"846"},{"tl":"eporeueto","en":"went away","gr":"ἐπορεύετο","pu":".","pa":"V-IIM/P-3S","st":"4198"}],"31":[{"tl":"Kai","en":"And","gr":"Καὶ","pu":null,"pa":"Conj","st":"2532"},{"tl":"katēlthen","en":"He went down","gr":"κατῆλθεν","pu":null,"pa":"V-AIA-3S","st":"2718"},{"tl":"eis","en":"to","gr":"εἰς","pu":null,"pa":"Prep","st":"1519"},{"tl":"Kapharnaoum","en":"Capernaum","gr":"Καφαρναοὺμ","pu":",","pa":"N-AFS","st":"2584"},{"tl":"polin","en":"a city","gr":"πόλιν","pu":null,"pa":"N-AFS","st":"4172"},{"tl":"tēs","en":" - ","gr":"τῆς","pu":null,"pa":"Art-GFS","st":"3588"},{"tl":"Galilaias","en":"of Galilee","gr":"Γαλιλαίας","pu":".","pa":"N-GFS","st":"1056"},{"tl":"kai","en":"And","gr":"καὶ","pu":null,"pa":"Conj","st":"2532"},{"tl":"ēn","en":"He was","gr":"ἦν","pu":null,"pa":"V-IIA-3S","st":"1510"},{"tl":"didaskōn","en":"teaching","gr":"διδάσκων","pu":null,"pa":"V-PPA-NMS","st":"1321"},{"tl":"autous","en":"them","gr":"αὐτοὺς","pu":null,"pa":"PPro-AM3P","st":"846"},{"tl":"en","en":"on","gr":"ἐν","pu":null,"pa":"Prep","st":"1722"},{"tl":"tois","en":"the","gr":"τοῖς","pu":null,"pa":"Art-DNP","st":"3588"},{"tl":"sabbasin","en":"Sabbaths","gr":"σάββασιν","pu":";","pa":"N-DNP","st":"4521"}],"32":[{"tl":"kai","en":"and","gr":"καὶ","pu":null,"pa":"Conj","st":"2532"},{"tl":"exeplēssonto","en":"they were astonished","gr":"ἐξεπλήσσοντο","pu":null,"pa":"V-IIM/P-3P","st":"1605"},{"tl":"epi","en":"at","gr":"ἐπὶ","pu":null,"pa":"Prep","st":"1909"},{"tl":"tē","en":"the","gr":"τῇ","pu":null,"pa":"Art-DFS","st":"3588"},{"tl":"didachē","en":"teaching","gr":"διδαχῇ","pu":null,"pa":"N-DFS","st":"1322"},{"tl":"autou","en":"of Him","gr":"αὐτοῦ","pu":",","pa":"PPro-GM3S","st":"846"},{"tl":"hoti","en":"for","gr":"ὅτι","pu":null,"pa":"Conj","st":"3754"},{"tl":"en","en":"with","gr":"ἐν","pu":null,"pa":"Prep","st":"1722"},{"tl":"exousia","en":"authority","gr":"ἐξουσίᾳ","pu":null,"pa":"N-DFS","st":"1849"},{"tl":"ēn","en":"was","gr":"ἦν","pu":null,"pa":"V-IIA-3S","st":"1510"},{"tl":"ho","en":"the","gr":"ὁ","pu":null,"pa":"Art-NMS","st":"3588"},{"tl":"logos","en":"message","gr":"λόγος","pu":null,"pa":"N-NMS","st":"3056"},{"tl":"autou","en":"of Him","gr":"αὐτοῦ","pu":".","pa":"PPro-GM3S","st":"846"}],"33":[{"tl":"Kai","en":"And","gr":"Καὶ","pu":null,"pa":"Conj","st":"2532"},{"tl":"en","en":"in","gr":"ἐν","pu":null,"pa":"Prep","st":"1722"},{"tl":"tē","en":"the","gr":"τῇ","pu":null,"pa":"Art-DFS","st":"3588"},{"tl":"synagōgē","en":"synagogue","gr":"συναγωγῇ","pu":null,"pa":"N-DFS","st":"4864"},{"tl":"ēn","en":"was","gr":"ἦν","pu":null,"pa":"V-IIA-3S","st":"1510"},{"tl":"anthrōpos","en":"a man","gr":"ἄνθρωπος","pu":null,"pa":"N-NMS","st":"444"},{"tl":"echōn","en":"having","gr":"ἔχων","pu":null,"pa":"V-PPA-NMS","st":"2192"},{"tl":"pneuma","en":"a spirit","gr":"πνεῦμα","pu":null,"pa":"N-ANS","st":"4151"},{"tl":"daimoniou","en":"of a demon","gr":"δαιμονίου","pu":null,"pa":"N-GNS","st":"1140"},{"tl":"akathartou","en":"unclean","gr":"ἀκαθάρτου","pu":";","pa":"Adj-GNS","st":"169"},{"tl":"kai","en":"and","gr":"καὶ","pu":null,"pa":"Conj","st":"2532"},{"tl":"anekraxen","en":"he cried out","gr":"ἀνέκραξεν","pu":null,"pa":"V-AIA-3S","st":"349"},{"tl":"phōnē","en":"in a voice","gr":"φωνῇ","pu":null,"pa":"N-DFS","st":"5456"},{"tl":"megalē","en":"loud","gr":"μεγάλῃ","pu":",","pa":"Adj-DFS","st":"3173"}],"34":[{"tl":"Ea","en":"Ha","gr":"Ἔα","pu":"!","pa":"I","st":"1436"},{"tl":"ti","en":"What","gr":"τί","pu":null,"pa":"IPro-NNS","st":"5101"},{"tl":"hēmin","en":"to us","gr":"ἡμῖν","pu":null,"pa":"PPro-D1P","st":"1473"},{"tl":"kai","en":"and","gr":"καὶ","pu":null,"pa":"Conj","st":"2532"},{"tl":"soi","en":"to You","gr":"σοί","pu":",","pa":"PPro-D2S","st":"4771"},{"tl":"Iēsou","en":"Jesus","gr":"Ἰησοῦ","pu":",","pa":"N-VMS","st":"2424"},{"tl":"Nazarēne","en":"of Nazareth","gr":"Ναζαρηνέ","pu":"?","pa":"N-VMS","st":"3479"},{"tl":"ēlthes","en":"Are You come","gr":"ἦλθες","pu":null,"pa":"V-AIA-2S","st":"2064"},{"tl":"apolesai","en":"to destroy","gr":"ἀπολέσαι","pu":null,"pa":"V-ANA","st":"622"},{"tl":"hēmas","en":"us","gr":"ἡμᾶς","pu":"?","pa":"PPro-A1P","st":"1473"},{"tl":"oida","en":"I know","gr":"οἶδά","pu":null,"pa":"V-RIA-1S","st":"1492"},{"tl":"se","en":"You","gr":"σε","pu":null,"pa":"PPro-A2S","st":"4771"},{"tl":"tis","en":"who","gr":"τίς","pu":null,"pa":"IPro-NMS","st":"5101"},{"tl":"ei","en":"are","gr":"εἶ","pu":",","pa":"V-PIA-2S","st":"1510"},{"tl":"ho","en":"the","gr":"ὁ","pu":null,"pa":"Art-NMS","st":"3588"},{"tl":"Hagios","en":"Holy [One]","gr":"Ἅγιος","pu":null,"pa":"Adj-NMS","st":"40"},{"tl":"tou","en":" - ","gr":"τοῦ","pu":null,"pa":"Art-GMS","st":"3588"},{"tl":"Theou","en":"of God","gr":"Θεοῦ","pu":".","pa":"N-GMS","st":"2316"}],"35":[{"tl":"Kai","en":"And","gr":"Καὶ","pu":null,"pa":"Conj","st":"2532"},{"tl":"epetimēsen","en":"rebuked","gr":"ἐπετίμησεν","pu":null,"pa":"V-AIA-3S","st":"2008"},{"tl":"autō","en":"him","gr":"αὐτῷ","pu":null,"pa":"PPro-DM3S","st":"846"},{"tl":"ho","en":" - ","gr":"ὁ","pu":null,"pa":"Art-NMS","st":"3588"},{"tl":"Iēsous","en":"Jesus","gr":"Ἰησοῦς","pu":",","pa":"N-NMS","st":"2424"},{"tl":"legōn","en":"saying","gr":"λέγων","pu":",","pa":"V-PPA-NMS","st":"3004"},{"tl":"Phimōthēti","en":"Be silent","gr":"Φιμώθητι","pu":null,"pa":"V-AMP-2S","st":"5392"},{"tl":"kai","en":"and","gr":"καὶ","pu":null,"pa":"Conj","st":"2532"},{"tl":"exelthe","en":"come forth","gr":"ἔξελθε","pu":null,"pa":"V-AMA-2S","st":"1831"},{"tl":"ap’","en":"out of","gr":"ἀπ’","pu":null,"pa":"Prep","st":"575"},{"tl":"autou","en":"him","gr":"αὐτοῦ","pu":"!","pa":"PPro-GM3S","st":"846"},{"tl":"kai","en":"And","gr":"καὶ","pu":null,"pa":"Conj","st":"2532"},{"tl":"rhipsan","en":"having thrown","gr":"ῥίψαν","pu":null,"pa":"V-APA-NNS","st":"4496"},{"tl":"auton","en":"him","gr":"αὐτὸν","pu":null,"pa":"PPro-AM3S","st":"846"},{"tl":"to","en":"the","gr":"τὸ","pu":null,"pa":"Art-NNS","st":"3588"},{"tl":"daimonion","en":"demon","gr":"δαιμόνιον","pu":null,"pa":"N-NNS","st":"1140"},{"tl":"eis","en":"into","gr":"εἰς","pu":null,"pa":"Prep","st":"1519"},{"tl":"to","en":"the","gr":"τὸ","pu":null,"pa":"Art-ANS","st":"3588"},{"tl":"meson","en":"midst","gr":"μέσον","pu":",","pa":"Adj-ANS","st":"3319"},{"tl":"exēlthen","en":"it came out","gr":"ἐξῆλθεν","pu":null,"pa":"V-AIA-3S","st":"1831"},{"tl":"ap’","en":"from","gr":"ἀπ’","pu":null,"pa":"Prep","st":"575"},{"tl":"autou","en":"him","gr":"αὐτοῦ","pu":",","pa":"PPro-GM3S","st":"846"},{"tl":"mēden","en":"in nothing","gr":"μηδὲν","pu":null,"pa":"Adj-ANS","st":"3367"},{"tl":"blapsan","en":"having hurt","gr":"βλάψαν","pu":null,"pa":"V-APA-NNS","st":"984"},{"tl":"auton","en":"him","gr":"αὐτόν","pu":".","pa":"PPro-AM3S","st":"846"}],"36":[{"tl":"Kai","en":"And","gr":"Καὶ","pu":null,"pa":"Conj","st":"2532"},{"tl":"egeneto","en":"came","gr":"ἐγένετο","pu":null,"pa":"V-AIM-3S","st":"1096"},{"tl":"thambos","en":"astonishment","gr":"θάμβος","pu":null,"pa":"N-NNS","st":"2285"},{"tl":"epi","en":"upon","gr":"ἐπὶ","pu":null,"pa":"Prep","st":"1909"},{"tl":"pantas","en":"all","gr":"πάντας","pu":",","pa":"Adj-AMP","st":"3956"},{"tl":"kai","en":"and","gr":"καὶ","pu":null,"pa":"Conj","st":"2532"},{"tl":"synelaloun","en":"they were speaking","gr":"συνελάλουν","pu":null,"pa":"V-IIA-3P","st":"4814"},{"tl":"pros","en":"to","gr":"πρὸς","pu":null,"pa":"Prep","st":"4314"},{"tl":"allēlous","en":"one another","gr":"ἀλλήλους","pu":",","pa":"RecPro-AMP","st":"240"},{"tl":"legontes","en":"saying","gr":"λέγοντες","pu":",","pa":"V-PPA-NMP","st":"3004"},{"tl":"Tis","en":"What","gr":"Τίς","pu":null,"pa":"IPro-NMS","st":"5101"},{"tl":"ho","en":" - ","gr":"ὁ","pu":null,"pa":"Art-NMS","st":"3588"},{"tl":"logos","en":"word","gr":"λόγος","pu":null,"pa":"N-NMS","st":"3056"},{"tl":"houtos","en":"[is] this","gr":"οὗτος","pu":",","pa":"DPro-NMS","st":"3778"},{"tl":"hoti","en":"that","gr":"ὅτι","pu":null,"pa":"Conj","st":"3754"},{"tl":"en","en":"with","gr":"ἐν","pu":null,"pa":"Prep","st":"1722"},{"tl":"exousia","en":"authority","gr":"ἐξουσίᾳ","pu":null,"pa":"N-DFS","st":"1849"},{"tl":"kai","en":"and","gr":"καὶ","pu":null,"pa":"Conj","st":"2532"},{"tl":"dynamei","en":"power","gr":"δυνάμει","pu":null,"pa":"N-DFS","st":"1411"},{"tl":"epitassei","en":"He commands","gr":"ἐπιτάσσει","pu":null,"pa":"V-PIA-3S","st":"2004"},{"tl":"tois","en":"the","gr":"τοῖς","pu":null,"pa":"Art-DNP","st":"3588"},{"tl":"akathartois","en":"unclean","gr":"ἀκαθάρτοις","pu":null,"pa":"Adj-DNP","st":"169"},{"tl":"pneumasin","en":"spirits","gr":"πνεύμασιν","pu":",","pa":"N-DNP","st":"4151"},{"tl":"kai","en":"and","gr":"καὶ","pu":null,"pa":"Conj","st":"2532"},{"tl":"exerchontai","en":"they come out","gr":"ἐξέρχονται","pu":"?","pa":"V-PIM/P-3P","st":"1831"}],"37":[{"tl":"kai","en":"And","gr":"καὶ","pu":null,"pa":"Conj","st":"2532"},{"tl":"exeporeueto","en":"was spreading","gr":"ἐξεπορεύετο","pu":null,"pa":"V-IIM/P-3S","st":"1607"},{"tl":"ēchos","en":"the report","gr":"ἦχος","pu":null,"pa":"N-NNS","st":"2279"},{"tl":"peri","en":"concerning","gr":"περὶ","pu":null,"pa":"Prep","st":"4012"},{"tl":"autou","en":"Him","gr":"αὐτοῦ","pu":null,"pa":"PPro-GM3S","st":"846"},{"tl":"eis","en":"into","gr":"εἰς","pu":null,"pa":"Prep","st":"1519"},{"tl":"panta","en":"every","gr":"πάντα","pu":null,"pa":"Adj-AMS","st":"3956"},{"tl":"topon","en":"place","gr":"τόπον","pu":null,"pa":"N-AMS","st":"5117"},{"tl":"tēs","en":"of the","gr":"τῆς","pu":null,"pa":"Art-GFS","st":"3588"},{"tl":"perichōrou","en":"surrounding region","gr":"περιχώρου","pu":".","pa":"Adj-GFS","st":"4066"}],"38":[{"tl":"Anastas","en":"Having risen up","gr":"Ἀναστὰς","pu":null,"pa":"V-APA-NMS","st":"450"},{"tl":"de","en":"then","gr":"δὲ","pu":null,"pa":"Conj","st":"1161"},{"tl":"apo","en":"out of","gr":"ἀπὸ","pu":null,"pa":"Prep","st":"575"},{"tl":"tēs","en":"the","gr":"τῆς","pu":null,"pa":"Art-GFS","st":"3588"},{"tl":"synagōgēs","en":"synagogue","gr":"συναγωγῆς","pu":",","pa":"N-GFS","st":"4864"},{"tl":"eisēlthen","en":"He entered","gr":"εἰσῆλθεν","pu":null,"pa":"V-AIA-3S","st":"1525"},{"tl":"eis","en":"into","gr":"εἰς","pu":null,"pa":"Prep","st":"1519"},{"tl":"tēn","en":"the","gr":"τὴν","pu":null,"pa":"Art-AFS","st":"3588"},{"tl":"oikian","en":"house","gr":"οἰκίαν","pu":null,"pa":"N-AFS","st":"3614"},{"tl":"Simōnos","en":"of Simon","gr":"Σίμωνος","pu":".","pa":"N-GMS","st":"4613"},{"tl":"penthera","en":"[The] mother-in-law","gr":"πενθερὰ","pu":null,"pa":"N-NFS","st":"3994"},{"tl":"de","en":"then","gr":"δὲ","pu":null,"pa":"Conj","st":"1161"},{"tl":"tou","en":" - ","gr":"τοῦ","pu":null,"pa":"Art-GMS","st":"3588"},{"tl":"Simōnos","en":"of Simon","gr":"Σίμωνος","pu":null,"pa":"N-GMS","st":"4613"},{"tl":"ēn","en":"was","gr":"ἦν","pu":null,"pa":"V-IIA-3S","st":"1510"},{"tl":"synechomenē","en":"oppressed with","gr":"συνεχομένη","pu":null,"pa":"V-PPM/P-NFS","st":"4912"},{"tl":"pyretō","en":"a fever","gr":"πυρετῷ","pu":null,"pa":"N-DMS","st":"4446"},{"tl":"megalō","en":"great","gr":"μεγάλῳ","pu":";","pa":"Adj-DMS","st":"3173"},{"tl":"kai","en":"and","gr":"καὶ","pu":null,"pa":"Conj","st":"2532"},{"tl":"ērōtēsan","en":"they appealed","gr":"ἠρώτησαν","pu":null,"pa":"V-AIA-3P","st":"2065"},{"tl":"auton","en":"to Him","gr":"αὐτὸν","pu":null,"pa":"PPro-AM3S","st":"846"},{"tl":"peri","en":"for","gr":"περὶ","pu":null,"pa":"Prep","st":"4012"},{"tl":"autēs","en":"her","gr":"αὐτῆς","pu":".","pa":"PPro-GF3S","st":"846"}],"39":[{"tl":"kai","en":"And","gr":"καὶ","pu":null,"pa":"Conj","st":"2532"},{"tl":"epistas","en":"having stood","gr":"ἐπιστὰς","pu":null,"pa":"V-APA-NMS","st":"2186"},{"tl":"epanō","en":"over","gr":"ἐπάνω","pu":null,"pa":"Prep","st":"1883"},{"tl":"autēs","en":"her","gr":"αὐτῆς","pu":",","pa":"PPro-GF3S","st":"846"},{"tl":"epetimēsen","en":"He rebuked","gr":"ἐπετίμησεν","pu":null,"pa":"V-AIA-3S","st":"2008"},{"tl":"tō","en":"the","gr":"τῷ","pu":null,"pa":"Art-DMS","st":"3588"},{"tl":"pyretō","en":"fever","gr":"πυρετῷ","pu":",","pa":"N-DMS","st":"4446"},{"tl":"kai","en":"and","gr":"καὶ","pu":null,"pa":"Conj","st":"2532"},{"tl":"aphēken","en":"it left","gr":"ἀφῆκεν","pu":null,"pa":"V-AIA-3S","st":"863"},{"tl":"autēn","en":"her","gr":"αὐτήν","pu":";","pa":"PPro-AF3S","st":"846"},{"tl":"parachrēma","en":"immediately","gr":"παραχρῆμα","pu":null,"pa":"Adv","st":"3916"},{"tl":"de","en":"then","gr":"δὲ","pu":null,"pa":"Conj","st":"1161"},{"tl":"anastasa","en":"having arisen","gr":"ἀναστᾶσα","pu":",","pa":"V-APA-NFS","st":"450"},{"tl":"diēkonei","en":"she began to serve","gr":"διηκόνει","pu":null,"pa":"V-IIA-3S","st":"1247"},{"tl":"autois","en":"them","gr":"αὐτοῖς","pu":".","pa":"PPro-DM3P","st":"846"}],"40":[{"tl":"Dynontos","en":"At the setting","gr":"Δύνοντος","pu":null,"pa":"V-PPA-GMS","st":"1416"},{"tl":"de","en":"now","gr":"δὲ","pu":null,"pa":"Conj","st":"1161"},{"tl":"tou","en":"of the","gr":"τοῦ","pu":null,"pa":"Art-GMS","st":"3588"},{"tl":"hēliou","en":"sun","gr":"ἡλίου","pu":",","pa":"N-GMS","st":"2246"},{"tl":"hapantes","en":"all","gr":"ἅπαντες","pu":null,"pa":"Adj-NMP","st":"537"},{"tl":"hosoi","en":"as many as","gr":"ὅσοι","pu":null,"pa":"RelPro-NMP","st":"3745"},{"tl":"eichon","en":"had [any]","gr":"εἶχον","pu":null,"pa":"V-IIA-3P","st":"2192"},{"tl":"asthenountas","en":"ailing","gr":"ἀσθενοῦντας","pu":null,"pa":"V-PPA-AMP","st":"770"},{"tl":"nosois","en":"with diseases","gr":"νόσοις","pu":null,"pa":"N-DFP","st":"3554"},{"tl":"poikilais","en":"various","gr":"ποικίλαις","pu":",","pa":"Adj-DFP","st":"4164"},{"tl":"ēgagon","en":"brought","gr":"ἤγαγον","pu":null,"pa":"V-AIA-3P","st":"71"},{"tl":"autous","en":"them","gr":"αὐτοὺς","pu":null,"pa":"PPro-AM3P","st":"846"},{"tl":"pros","en":"to","gr":"πρὸς","pu":null,"pa":"Prep","st":"4314"},{"tl":"auton","en":"Him","gr":"αὐτόν","pu":",","pa":"PPro-AM3S","st":"846"},{"tl":"ho","en":" - ","gr":"ὁ","pu":null,"pa":"Art-NMS","st":"3588"},{"tl":"de","en":"and","gr":"δὲ","pu":null,"pa":"Conj","st":"1161"},{"tl":"heni","en":"on one","gr":"ἑνὶ","pu":null,"pa":"Adj-DMS","st":"1520"},{"tl":"hekastō","en":"each","gr":"ἑκάστῳ","pu":null,"pa":"Adj-DMS","st":"1538"},{"tl":"autōn","en":"of them","gr":"αὐτῶν","pu":",","pa":"PPro-GM3P","st":"846"},{"tl":"tas","en":"the","gr":"τὰς","pu":null,"pa":"Art-AFP","st":"3588"},{"tl":"cheiras","en":"hands","gr":"χεῖρας","pu":null,"pa":"N-AFP","st":"5495"},{"tl":"epititheis","en":"having laid","gr":"ἐπιτιθεὶς","pu":",","pa":"V-PPA-NMS","st":"2007"},{"tl":"etherapeuen","en":"He would heal","gr":"ἐθεράπευεν","pu":null,"pa":"V-IIA-3S","st":"2323"},{"tl":"autous","en":"them","gr":"αὐτούς","pu":".","pa":"PPro-AM3P","st":"846"}],"41":[{"tl":"exērcheto","en":"Were going out","gr":"ἐξήρχετο","pu":null,"pa":"V-IIM/P-3S","st":"1831"},{"tl":"de","en":"now","gr":"δὲ","pu":null,"pa":"Conj","st":"1161"},{"tl":"kai","en":"also","gr":"καὶ","pu":null,"pa":"Conj","st":"2532"},{"tl":"daimonia","en":"demons","gr":"δαιμόνια","pu":null,"pa":"N-NNP","st":"1140"},{"tl":"apo","en":"from","gr":"ἀπὸ","pu":null,"pa":"Prep","st":"575"},{"tl":"pollōn","en":"many","gr":"πολλῶν","pu":",","pa":"Adj-GMP","st":"4183"},{"tl":"kraugazonta","en":"crying out","gr":"κραυγάζοντα","pu":null,"pa":"V-PPA-NNP","st":"2905"},{"tl":"kai","en":"and","gr":"καὶ","pu":null,"pa":"Conj","st":"2532"},{"tl":"legonta","en":"saying","gr":"λέγοντα","pu":null,"pa":"V-PPA-NNP","st":"3004"},{"tl":"hoti","en":" - ","gr":"ὅτι","pu":",","pa":"Conj","st":"3754"},{"tl":"Sy","en":"You","gr":"Σὺ","pu":null,"pa":"PPro-N2S","st":"4771"},{"tl":"ei","en":"are","gr":"εἶ","pu":null,"pa":"V-PIA-2S","st":"1510"},{"tl":"ho","en":"the","gr":"ὁ","pu":null,"pa":"Art-NMS","st":"3588"},{"tl":"Huios","en":"Son","gr":"Υἱὸς","pu":null,"pa":"N-NMS","st":"5207"},{"tl":"tou","en":" - ","gr":"τοῦ","pu":null,"pa":"Art-GMS","st":"3588"},{"tl":"Theou","en":"of God","gr":"Θεοῦ","pu":".","pa":"N-GMS","st":"2316"},{"tl":"kai","en":"And","gr":"καὶ","pu":null,"pa":"Conj","st":"2532"},{"tl":"epitimōn","en":"rebuking [them]","gr":"ἐπιτιμῶν","pu":",","pa":"V-PPA-NMS","st":"2008"},{"tl":"ouk","en":"not","gr":"οὐκ","pu":null,"pa":"Adv","st":"3756"},{"tl":"eia","en":"did He allow","gr":"εἴα","pu":null,"pa":"V-IIA-3S","st":"1439"},{"tl":"auta","en":"them","gr":"αὐτὰ","pu":null,"pa":"PPro-AN3P","st":"846"},{"tl":"lalein","en":"to speak","gr":"λαλεῖν","pu":",","pa":"V-PNA","st":"2980"},{"tl":"hoti","en":"because","gr":"ὅτι","pu":null,"pa":"Conj","st":"3754"},{"tl":"ēdeisan","en":"they knew","gr":"ᾔδεισαν","pu":null,"pa":"V-LIA-3P","st":"1492"},{"tl":"ton","en":"the","gr":"τὸν","pu":null,"pa":"Art-AMS","st":"3588"},{"tl":"Christon","en":"Christ","gr":"Χριστὸν","pu":null,"pa":"N-AMS","st":"5547"},{"tl":"auton","en":"Him","gr":"αὐτὸν","pu":null,"pa":"PPro-AM3S","st":"846"},{"tl":"einai","en":"to be","gr":"εἶναι","pu":".","pa":"V-PNA","st":"1510"}],"42":[{"tl":"Genomenēs","en":"Having arrived","gr":"Γενομένης","pu":null,"pa":"V-APM-GFS","st":"1096"},{"tl":"de","en":"now","gr":"δὲ","pu":null,"pa":"Conj","st":"1161"},{"tl":"hēmeras","en":"daybreak","gr":"ἡμέρας","pu":",","pa":"N-GFS","st":"2250"},{"tl":"exelthōn","en":"having gone out","gr":"ἐξελθὼν","pu":",","pa":"V-APA-NMS","st":"1831"},{"tl":"eporeuthē","en":"He went","gr":"ἐπορεύθη","pu":null,"pa":"V-AIP-3S","st":"4198"},{"tl":"eis","en":"into","gr":"εἰς","pu":null,"pa":"Prep","st":"1519"},{"tl":"erēmon","en":"a solitary","gr":"ἔρημον","pu":null,"pa":"Adj-AMS","st":"2048"},{"tl":"topon","en":"place","gr":"τόπον","pu":",","pa":"N-AMS","st":"5117"},{"tl":"kai","en":"and","gr":"καὶ","pu":null,"pa":"Conj","st":"2532"},{"tl":"hoi","en":"the","gr":"οἱ","pu":null,"pa":"Art-NMP","st":"3588"},{"tl":"ochloi","en":"crowds","gr":"ὄχλοι","pu":null,"pa":"N-NMP","st":"3793"},{"tl":"epezētoun","en":"were seeking","gr":"ἐπεζήτουν","pu":null,"pa":"V-IIA-3P","st":"1934"},{"tl":"auton","en":"Him","gr":"αὐτόν","pu":",","pa":"PPro-AM3S","st":"846"},{"tl":"kai","en":"and","gr":"καὶ","pu":null,"pa":"Conj","st":"2532"},{"tl":"ēlthon","en":"they came","gr":"ἦλθον","pu":null,"pa":"V-AIA-3P","st":"2064"},{"tl":"heōs","en":"up to","gr":"ἕως","pu":null,"pa":"Prep","st":"2193"},{"tl":"autou","en":"Him","gr":"αὐτοῦ","pu":null,"pa":"PPro-GM3S","st":"846"},{"tl":"kai","en":"and","gr":"καὶ","pu":null,"pa":"Conj","st":"2532"},{"tl":"kateichon","en":"were detaining","gr":"κατεῖχον","pu":null,"pa":"V-IIA-3P","st":"2722"},{"tl":"auton","en":"Him","gr":"αὐτὸν","pu":",","pa":"PPro-AM3S","st":"846"},{"tl":"tou","en":"of the","gr":"τοῦ","pu":null,"pa":"Art-GNS","st":"3588"},{"tl":"mē","en":"not","gr":"μὴ","pu":null,"pa":"Adv","st":"3361"},{"tl":"poreuesthai","en":"to go","gr":"πορεύεσθαι","pu":null,"pa":"V-PNM/P","st":"4198"},{"tl":"ap’","en":"from","gr":"ἀπ’","pu":null,"pa":"Prep","st":"575"},{"tl":"autōn","en":"them","gr":"αὐτῶν","pu":".","pa":"PPro-GM3P","st":"846"}],"43":[{"tl":"ho","en":" - ","gr":"ὁ","pu":null,"pa":"Art-NMS","st":"3588"},{"tl":"de","en":"But","gr":"δὲ","pu":null,"pa":"Conj","st":"1161"},{"tl":"eipen","en":"He said","gr":"εἶπεν","pu":null,"pa":"V-AIA-3S","st":"2036"},{"tl":"pros","en":"to","gr":"πρὸς","pu":null,"pa":"Prep","st":"4314"},{"tl":"autous","en":"them","gr":"αὐτοὺς","pu":null,"pa":"PPro-AM3P","st":"846"},{"tl":"hoti","en":" - ","gr":"ὅτι","pu":",","pa":"Conj","st":"3754"},{"tl":"Kai","en":"Also","gr":"Καὶ","pu":null,"pa":"Conj","st":"2532"},{"tl":"tais","en":"to the","gr":"ταῖς","pu":null,"pa":"Art-DFP","st":"3588"},{"tl":"heterais","en":"other","gr":"ἑτέραις","pu":null,"pa":"Adj-DFP","st":"2087"},{"tl":"polesin","en":"towns","gr":"πόλεσιν","pu":null,"pa":"N-DFP","st":"4172"},{"tl":"euangelisasthai","en":"to preach [the] good news","gr":"εὐαγγελίσασθαί","pu":null,"pa":"V-ANM","st":"2097"},{"tl":"me","en":"Me","gr":"με","pu":null,"pa":"PPro-A1S","st":"1473"},{"tl":"dei","en":"it behooves","gr":"δεῖ","pu":",","pa":"V-PIA-3S","st":"1163"},{"tl":"tēn","en":"of the","gr":"τὴν","pu":null,"pa":"Art-AFS","st":"3588"},{"tl":"basileian","en":"kingdom","gr":"βασιλείαν","pu":null,"pa":"N-AFS","st":"932"},{"tl":"tou","en":" - ","gr":"τοῦ","pu":null,"pa":"Art-GMS","st":"3588"},{"tl":"Theou","en":"of God","gr":"Θεοῦ","pu":";","pa":"N-GMS","st":"2316"},{"tl":"hoti","en":"because","gr":"ὅτι","pu":null,"pa":"Conj","st":"3754"},{"tl":"epi","en":"for","gr":"ἐπὶ","pu":null,"pa":"Prep","st":"1909"},{"tl":"touto","en":"this","gr":"τοῦτο","pu":null,"pa":"DPro-ANS","st":"3778"},{"tl":"apestalēn","en":"have I been sent forth","gr":"ἀπεστάλην","pu":".","pa":"V-AIP-1S","st":"649"}],"44":[{"tl":"Kai","en":"And","gr":"Καὶ","pu":null,"pa":"Conj","st":"2532"},{"tl":"ēn","en":"He was","gr":"ἦν","pu":null,"pa":"V-IIA-3S","st":"1510"},{"tl":"kēryssōn","en":"preaching","gr":"κηρύσσων","pu":null,"pa":"V-PPA-NMS","st":"2784"},{"tl":"eis","en":"in","gr":"εἰς","pu":null,"pa":"Prep","st":"1519"},{"tl":"tas","en":"the","gr":"τὰς","pu":null,"pa":"Art-AFP","st":"3588"},{"tl":"synagōgas","en":"synagogues","gr":"συναγωγὰς","pu":null,"pa":"N-AFP","st":"4864"},{"tl":"tēs","en":" - ","gr":"τῆς","pu":null,"pa":"Art-GFS","st":"3588"},{"tl":"Ioudaias","en":"of Judea","gr":"Ἰουδαίας","pu":".","pa":"N-GFS","st":"2449"}]}}