{"chapter":"26","verses":{"1":[{"tl":"Agrippas","en":"Agrippa","gr":"Ἀγρίππας","pu":null,"pa":"N-NMS","st":"67"},{"tl":"de","en":"then","gr":"δὲ","pu":null,"pa":"Conj","st":"1161"},{"tl":"pros","en":"to","gr":"πρὸς","pu":null,"pa":"Prep","st":"4314"},{"tl":"ton","en":" - ","gr":"τὸν","pu":null,"pa":"Art-AMS","st":"3588"},{"tl":"Paulon","en":"Paul","gr":"Παῦλον","pu":null,"pa":"N-AMS","st":"3972"},{"tl":"ephē","en":"was saying","gr":"ἔφη","pu":",","pa":"V-IIA-3S","st":"5346"},{"tl":"Epitrepetai","en":"It is permitted","gr":"Ἐπιτρέπεταί","pu":null,"pa":"V-PIM/P-3S","st":"2010"},{"tl":"soi","en":"you","gr":"σοι","pu":null,"pa":"PPro-D2S","st":"4771"},{"tl":"hyper","en":"for","gr":"ὑπὲρ","pu":null,"pa":"Prep","st":"5228"},{"tl":"seautou","en":"yourself","gr":"σεαυτοῦ","pu":null,"pa":"PPro-GM2S","st":"4572"},{"tl":"legein","en":"to speak","gr":"λέγειν","pu":".","pa":"V-PNA","st":"3004"},{"tl":"Tote","en":"Then","gr":"Τότε","pu":null,"pa":"Adv","st":"5119"},{"tl":"ho","en":" - ","gr":"ὁ","pu":null,"pa":"Art-NMS","st":"3588"},{"tl":"Paulos","en":"Paul","gr":"Παῦλος","pu":",","pa":"N-NMS","st":"3972"},{"tl":"ekteinas","en":"having stretched out","gr":"ἐκτείνας","pu":null,"pa":"V-APA-NMS","st":"1614"},{"tl":"tēn","en":"the","gr":"τὴν","pu":null,"pa":"Art-AFS","st":"3588"},{"tl":"cheira","en":"hand","gr":"χεῖρα","pu":",","pa":"N-AFS","st":"5495"},{"tl":"apelogeito","en":"began his defense","gr":"ἀπελογεῖτο","pu":":","pa":"V-IIM/P-3S","st":"626"}],"2":[{"tl":"Peri","en":"Concerning","gr":"Περὶ","pu":null,"pa":"Prep","st":"4012"},{"tl":"pantōn","en":"all","gr":"πάντων","pu":null,"pa":"Adj-GNP","st":"3956"},{"tl":"hōn","en":"of which","gr":"ὧν","pu":null,"pa":"RelPro-GNP","st":"3739"},{"tl":"enkaloumai","en":"I am accused","gr":"ἐγκαλοῦμαι","pu":null,"pa":"V-PIM/P-1S","st":"1458"},{"tl":"hypo","en":"by","gr":"ὑπὸ","pu":null,"pa":"Prep","st":"5259"},{"tl":"Ioudaiōn","en":"[the] Jews","gr":"Ἰουδαίων","pu":",","pa":"Adj-GMP","st":"2453"},{"tl":"basileu","en":"King","gr":"βασιλεῦ","pu":null,"pa":"N-VMS","st":"935"},{"tl":"Agrippa","en":"Agrippa","gr":"Ἀγρίππα","pu":",","pa":"N-VMS","st":"67"},{"tl":"hēgēmai","en":"I esteem","gr":"ἥγημαι","pu":null,"pa":"V-RIM/P-1S","st":"2233"},{"tl":"emauton","en":"myself","gr":"ἐμαυτὸν","pu":null,"pa":"PPro-AM1S","st":"1683"},{"tl":"makarion","en":"fortunate","gr":"μακάριον","pu":null,"pa":"Adj-AMS","st":"3107"},{"tl":"epi","en":"before","gr":"ἐπὶ","pu":null,"pa":"Prep","st":"1909"},{"tl":"sou","en":"you","gr":"σοῦ","pu":",","pa":"PPro-G2S","st":"4771"},{"tl":"mellōn","en":"being about","gr":"μέλλων","pu":null,"pa":"V-PPA-NMS","st":"3195"},{"tl":"sēmeron","en":"today","gr":"σήμερον","pu":null,"pa":"Adv","st":"4594"},{"tl":"apologeisthai","en":"to defend myself","gr":"ἀπολογεῖσθαι","pu":".","pa":"V-PNM/P","st":"626"}],"3":[{"tl":"malista","en":"Especially","gr":"μάλιστα","pu":null,"pa":"Adv","st":"3122"},{"tl":"gnōstēn","en":"acquainted","gr":"γνώστην","pu":null,"pa":"N-AMS","st":"1109"},{"tl":"onta","en":"being","gr":"ὄντα","pu":null,"pa":"V-PPA-AMS","st":"1510"},{"tl":"se","en":"you","gr":"σε","pu":null,"pa":"PPro-A2S","st":"4771"},{"tl":"pantōn","en":"with all","gr":"πάντων","pu":null,"pa":"Adj-GNP","st":"3956"},{"tl":"tōn","en":"the","gr":"τῶν","pu":null,"pa":"Art-GNP","st":"3588"},{"tl":"kata","en":"of","gr":"κατὰ","pu":null,"pa":"Prep","st":"2596"},{"tl":"Ioudaious","en":"[the] Jews","gr":"Ἰουδαίους","pu":null,"pa":"Adj-AMP","st":"2453"},{"tl":"ethōn","en":"customs","gr":"ἐθῶν","pu":",","pa":"N-GNP","st":"1485"},{"tl":"te","en":"and","gr":"τε","pu":null,"pa":"Conj","st":"5037"},{"tl":"kai","en":"also","gr":"καὶ","pu":null,"pa":"Conj","st":"2532"},{"tl":"zētēmatōn","en":"controversies","gr":"ζητημάτων","pu":";","pa":"N-GNP","st":"2213"},{"tl":"dio","en":"therefore","gr":"διὸ","pu":null,"pa":"Conj","st":"1352"},{"tl":"deomai","en":"I implore [you]","gr":"δέομαι","pu":null,"pa":"V-PIM/P-1S","st":"1189"},{"tl":"makrothymōs","en":"patiently","gr":"μακροθύμως","pu":null,"pa":"Adv","st":"3116"},{"tl":"akousai","en":"to hear","gr":"ἀκοῦσαί","pu":null,"pa":"V-ANA","st":"191"},{"tl":"mou","en":"me","gr":"μου","pu":".","pa":"PPro-G1S","st":"1473"}],"4":[{"tl":"Tēn","en":"The","gr":"Τὴν","pu":null,"pa":"Art-AFS","st":"3588"},{"tl":"men","en":"indeed","gr":"μὲν","pu":null,"pa":"Conj","st":"3303"},{"tl":"oun","en":"then","gr":"οὖν","pu":null,"pa":"Conj","st":"3767"},{"tl":"biōsin","en":"manner of life","gr":"βίωσίν","pu":null,"pa":"N-AFS","st":"981"},{"tl":"mou","en":"of me","gr":"μου","pu":",","pa":"PPro-G1S","st":"1473"},{"tl":"tēn","en":"which [is]","gr":"‹τὴν›","pu":null,"pa":"Art-AFS","st":"3588"},{"tl":"ek","en":"from","gr":"ἐκ","pu":null,"pa":"Prep","st":"1537"},{"tl":"neotētos","en":"youth","gr":"νεότητος","pu":",","pa":"N-GFS","st":"3503"},{"tl":"tēn","en":" - ","gr":"τὴν","pu":null,"pa":"Art-AFS","st":"3588"},{"tl":"ap’","en":"from [its]","gr":"ἀπ’","pu":null,"pa":"Prep","st":"575"},{"tl":"archēs","en":"beginning","gr":"ἀρχῆς","pu":null,"pa":"N-GFS","st":"746"},{"tl":"genomenēn","en":"having been","gr":"γενομένην","pu":null,"pa":"V-APM-AFS","st":"1096"},{"tl":"en","en":"among","gr":"ἐν","pu":null,"pa":"Prep","st":"1722"},{"tl":"tō","en":"the","gr":"τῷ","pu":null,"pa":"Art-DNS","st":"3588"},{"tl":"ethnei","en":"nation","gr":"ἔθνει","pu":null,"pa":"N-DNS","st":"1484"},{"tl":"mou","en":"of me","gr":"μου","pu":",","pa":"PPro-G1S","st":"1473"},{"tl":"en","en":"in","gr":"ἔν","pu":null,"pa":"Prep","st":"1722"},{"tl":"te","en":"also","gr":"τε","pu":null,"pa":"Conj","st":"5037"},{"tl":"Hierosolymois","en":"Jerusalem","gr":"Ἱεροσολύμοις","pu":",","pa":"N-DNP","st":"2414"},{"tl":"isasi","en":"know","gr":"ἴσασι","pu":null,"pa":"V-RIA-3P","st":"1492"},{"tl":"pantes","en":"all","gr":"πάντες","pu":null,"pa":"Adj-NMP","st":"3956"},{"tl":"hoi","en":"the","gr":"[οἱ]","pu":null,"pa":"Art-NMP","st":"3588"},{"tl":"Ioudaioi","en":"Jews","gr":"Ἰουδαῖοι","pu":",","pa":"Adj-NMP","st":"2453"}],"5":[{"tl":"proginōskontes","en":"knowing","gr":"προγινώσκοντές","pu":null,"pa":"V-PPA-NMP","st":"4267"},{"tl":"me","en":"me","gr":"με","pu":null,"pa":"PPro-A1S","st":"1473"},{"tl":"anōthen","en":"from the first","gr":"ἄνωθεν","pu":",","pa":"Adv","st":"509"},{"tl":"ean","en":"if","gr":"ἐὰν","pu":null,"pa":"Conj","st":"1437"},{"tl":"thelōsi","en":"they would be willing","gr":"θέλωσι","pu":null,"pa":"V-PSA-3P","st":"2309"},{"tl":"martyrein","en":"to testify","gr":"μαρτυρεῖν","pu":",","pa":"V-PNA","st":"3140"},{"tl":"hoti","en":"that","gr":"ὅτι","pu":null,"pa":"Conj","st":"3754"},{"tl":"kata","en":"according to","gr":"κατὰ","pu":null,"pa":"Prep","st":"2596"},{"tl":"tēn","en":"the","gr":"τὴν","pu":null,"pa":"Art-AFS","st":"3588"},{"tl":"akribestatēn","en":"strictest","gr":"ἀκριβεστάτην","pu":null,"pa":"Adj-AFS-S","st":"196"},{"tl":"hairesin","en":"sect","gr":"αἵρεσιν","pu":null,"pa":"N-AFS","st":"139"},{"tl":"tēs","en":" - ","gr":"τῆς","pu":null,"pa":"Art-GFS","st":"3588"},{"tl":"hēmeteras","en":"of our","gr":"ἡμετέρας","pu":null,"pa":"PPro-GF1P","st":"2251"},{"tl":"thrēskeias","en":"religion","gr":"θρησκείας","pu":null,"pa":"N-GFS","st":"2356"},{"tl":"ezēsa","en":"I lived [as]","gr":"ἔζησα","pu":null,"pa":"V-AIA-1S","st":"2198"},{"tl":"Pharisaios","en":"a Pharisee","gr":"Φαρισαῖος","pu":".","pa":"N-NMS","st":"5330"}],"6":[{"tl":"Kai","en":"And","gr":"Καὶ","pu":null,"pa":"Conj","st":"2532"},{"tl":"nyn","en":"now","gr":"νῦν","pu":null,"pa":"Adv","st":"3568"},{"tl":"ep’","en":"for [the]","gr":"ἐπ’","pu":null,"pa":"Prep","st":"1909"},{"tl":"elpidi","en":"hope","gr":"ἐλπίδι","pu":null,"pa":"N-DFS","st":"1680"},{"tl":"tēs","en":"of the","gr":"τῆς","pu":null,"pa":"Art-GFS","st":"3588"},{"tl":"eis","en":"to","gr":"εἰς","pu":null,"pa":"Prep","st":"1519"},{"tl":"tous","en":"the","gr":"τοὺς","pu":null,"pa":"Art-AMP","st":"3588"},{"tl":"pateras","en":"fathers","gr":"πατέρας","pu":null,"pa":"N-AMP","st":"3962"},{"tl":"hēmōn","en":"of us","gr":"ἡμῶν","pu":null,"pa":"PPro-G1P","st":"1473"},{"tl":"epangelias","en":"promise","gr":"ἐπαγγελίας","pu":null,"pa":"N-GFS","st":"1860"},{"tl":"genomenēs","en":"having been made","gr":"γενομένης","pu":null,"pa":"V-APM-GFS","st":"1096"},{"tl":"hypo","en":"by","gr":"ὑπὸ","pu":null,"pa":"Prep","st":"5259"},{"tl":"tou","en":" - ","gr":"τοῦ","pu":null,"pa":"Art-GMS","st":"3588"},{"tl":"Theou","en":"God","gr":"Θεοῦ","pu":",","pa":"N-GMS","st":"2316"},{"tl":"hestēka","en":"I stand","gr":"ἕστηκα","pu":null,"pa":"V-RIA-1S","st":"2476"},{"tl":"krinomenos","en":"being judged","gr":"κρινόμενος","pu":",","pa":"V-PPM/P-NMS","st":"2919"}],"7":[{"tl":"eis","en":"to","gr":"εἰς","pu":null,"pa":"Prep","st":"1519"},{"tl":"hēn","en":"which","gr":"ἣν","pu":null,"pa":"RelPro-AFS","st":"3739"},{"tl":"to","en":"the","gr":"τὸ","pu":null,"pa":"Art-NNS","st":"3588"},{"tl":"dōdekaphylon","en":"twelve tribes","gr":"δωδεκάφυλον","pu":null,"pa":"N-NNS","st":"1429"},{"tl":"hēmōn","en":"of us","gr":"ἡμῶν","pu":null,"pa":"PPro-G1P","st":"1473"},{"tl":"en","en":"in","gr":"ἐν","pu":null,"pa":"Prep","st":"1722"},{"tl":"ekteneia","en":"earnestness","gr":"ἐκτενείᾳ","pu":",","pa":"N-DFS","st":"1616"},{"tl":"nykta","en":"night","gr":"νύκτα","pu":null,"pa":"N-AFS","st":"3571"},{"tl":"kai","en":"and","gr":"καὶ","pu":null,"pa":"Conj","st":"2532"},{"tl":"hēmeran","en":"day","gr":"ἡμέραν","pu":",","pa":"N-AFS","st":"2250"},{"tl":"latreuon","en":"serving","gr":"λατρεῦον","pu":",","pa":"V-PPA-NNS","st":"3000"},{"tl":"elpizei","en":"hope","gr":"ἐλπίζει","pu":null,"pa":"V-PIA-3S","st":"1679"},{"tl":"katantēsai","en":"to attain","gr":"καταντῆσαι","pu":";","pa":"V-ANA","st":"2658"},{"tl":"peri","en":"concerning","gr":"περὶ","pu":null,"pa":"Prep","st":"4012"},{"tl":"hēs","en":"which","gr":"ἧς","pu":null,"pa":"RelPro-GFS","st":"3739"},{"tl":"elpidos","en":"hope","gr":"ἐλπίδος","pu":null,"pa":"N-GFS","st":"1680"},{"tl":"enkaloumai","en":"I am accused","gr":"ἐγκαλοῦμαι","pu":null,"pa":"V-PIM/P-1S","st":"1458"},{"tl":"hypo","en":"by","gr":"ὑπὸ","pu":null,"pa":"Prep","st":"5259"},{"tl":"Ioudaiōn","en":"the Jews","gr":"Ἰουδαίων","pu":",","pa":"Adj-GMP","st":"2453"},{"tl":"basileu","en":"O king","gr":"βασιλεῦ","pu":".","pa":"N-VMS","st":"935"}],"8":[{"tl":"ti","en":"Why","gr":"τί","pu":null,"pa":"IPro-ANS","st":"5101"},{"tl":"apiston","en":"incredible","gr":"ἄπιστον","pu":null,"pa":"Adj-NNS","st":"571"},{"tl":"krinetai","en":"is it judged","gr":"κρίνεται","pu":null,"pa":"V-PIM/P-3S","st":"2919"},{"tl":"par’","en":"by","gr":"παρ’","pu":null,"pa":"Prep","st":"3844"},{"tl":"hymin","en":"you","gr":"ὑμῖν","pu":null,"pa":"PPro-D2P","st":"4771"},{"tl":"ei","en":"if","gr":"εἰ","pu":null,"pa":"Conj","st":"1487"},{"tl":"ho","en":" - ","gr":"ὁ","pu":null,"pa":"Art-NMS","st":"3588"},{"tl":"Theos","en":"God","gr":"Θεὸς","pu":null,"pa":"N-NMS","st":"2316"},{"tl":"nekrous","en":"[the] dead","gr":"νεκροὺς","pu":null,"pa":"Adj-AMP","st":"3498"},{"tl":"egeirei","en":"raises","gr":"ἐγείρει","pu":"?","pa":"V-PIA-3S","st":"1453"}],"9":[{"tl":"Egō","en":"I","gr":"Ἐγὼ","pu":null,"pa":"PPro-N1S","st":"1473"},{"tl":"men","en":"indeed","gr":"μὲν","pu":null,"pa":"Conj","st":"3303"},{"tl":"oun","en":"therefore","gr":"οὖν","pu":null,"pa":"Conj","st":"3767"},{"tl":"edoxa","en":"thought","gr":"ἔδοξα","pu":null,"pa":"V-AIA-1S","st":"1380"},{"tl":"emautō","en":"in myself","gr":"ἐμαυτῷ","pu":null,"pa":"PPro-DM1S","st":"1683"},{"tl":"pros","en":"to","gr":"πρὸς","pu":null,"pa":"Prep","st":"4314"},{"tl":"to","en":"the","gr":"τὸ","pu":null,"pa":"Art-ANS","st":"3588"},{"tl":"onoma","en":"name","gr":"ὄνομα","pu":null,"pa":"N-ANS","st":"3686"},{"tl":"Iēsou","en":"of Jesus","gr":"Ἰησοῦ","pu":null,"pa":"N-GMS","st":"2424"},{"tl":"tou","en":" - ","gr":"τοῦ","pu":null,"pa":"Art-GMS","st":"3588"},{"tl":"Nazōraiou","en":"of Nazareth","gr":"Ναζωραίου","pu":",","pa":"N-GMS","st":"3480"},{"tl":"dein","en":"I ought","gr":"δεῖν","pu":null,"pa":"V-PNA","st":"1163"},{"tl":"polla","en":"many things","gr":"πολλὰ","pu":null,"pa":"Adj-ANP","st":"4183"},{"tl":"enantia","en":"contrary","gr":"ἐναντία","pu":null,"pa":"Adj-ANP","st":"1727"},{"tl":"praxai","en":"to do","gr":"πρᾶξαι","pu":",","pa":"V-ANA","st":"4238"}],"10":[{"tl":"ho","en":"which","gr":"ὃ","pu":null,"pa":"RelPro-ANS","st":"3739"},{"tl":"kai","en":"also","gr":"καὶ","pu":null,"pa":"Conj","st":"2532"},{"tl":"epoiēsa","en":"I did","gr":"ἐποίησα","pu":null,"pa":"V-AIA-1S","st":"4160"},{"tl":"en","en":"in","gr":"ἐν","pu":null,"pa":"Prep","st":"1722"},{"tl":"Hierosolymois","en":"Jerusalem","gr":"Ἱεροσολύμοις","pu":";","pa":"N-DNP","st":"2414"},{"tl":"kai","en":"and","gr":"καὶ","pu":null,"pa":"Conj","st":"2532"},{"tl":"pollous","en":"many","gr":"πολλούς","pu":null,"pa":"Adj-AMP","st":"4183"},{"tl":"te","en":"also","gr":"τε","pu":null,"pa":"Conj","st":"5037"},{"tl":"tōn","en":"of the","gr":"τῶν","pu":null,"pa":"Art-GMP","st":"3588"},{"tl":"hagiōn","en":"saints","gr":"ἁγίων","pu":null,"pa":"Adj-GMP","st":"40"},{"tl":"egō","en":"I","gr":"ἐγὼ","pu":null,"pa":"PPro-N1S","st":"1473"},{"tl":"en","en":"in","gr":"ἐν","pu":null,"pa":"Prep","st":"1722"},{"tl":"phylakais","en":"prisons","gr":"φυλακαῖς","pu":null,"pa":"N-DFP","st":"5438"},{"tl":"katekleisa","en":"locked up","gr":"κατέκλεισα","pu":",","pa":"V-AIA-1S","st":"2623"},{"tl":"tēn","en":"the","gr":"τὴν","pu":null,"pa":"Art-AFS","st":"3588"},{"tl":"para","en":"from","gr":"παρὰ","pu":null,"pa":"Prep","st":"3844"},{"tl":"tōn","en":"the","gr":"τῶν","pu":null,"pa":"Art-GMP","st":"3588"},{"tl":"archiereōn","en":"chief priests","gr":"ἀρχιερέων","pu":null,"pa":"N-GMP","st":"749"},{"tl":"exousian","en":"authority","gr":"ἐξουσίαν","pu":null,"pa":"N-AFS","st":"1849"},{"tl":"labōn","en":"having received","gr":"λαβών","pu":";","pa":"V-APA-NMS","st":"2983"},{"tl":"anairoumenōn","en":"being put to death","gr":"ἀναιρουμένων","pu":null,"pa":"V-PPM/P-GMP","st":"337"},{"tl":"te","en":"then","gr":"τε","pu":null,"pa":"Conj","st":"5037"},{"tl":"autōn","en":"they","gr":"αὐτῶν","pu":",","pa":"PPro-GM3P","st":"846"},{"tl":"katēnenka","en":"I cast against [them]","gr":"κατήνεγκα","pu":null,"pa":"V-AIA-1S","st":"2702"},{"tl":"psēphon","en":"a vote","gr":"ψῆφον","pu":".","pa":"N-AFS","st":"5586"}],"11":[{"tl":"kai","en":"And","gr":"καὶ","pu":null,"pa":"Conj","st":"2532"},{"tl":"kata","en":"in","gr":"κατὰ","pu":null,"pa":"Prep","st":"2596"},{"tl":"pasas","en":"all","gr":"πάσας","pu":null,"pa":"Adj-AFP","st":"3956"},{"tl":"tas","en":"the","gr":"τὰς","pu":null,"pa":"Art-AFP","st":"3588"},{"tl":"synagōgas","en":"synagogues","gr":"συναγωγὰς","pu":",","pa":"N-AFP","st":"4864"},{"tl":"pollakis","en":"often","gr":"πολλάκις","pu":null,"pa":"Adv","st":"4178"},{"tl":"timōrōn","en":"punishing","gr":"τιμωρῶν","pu":null,"pa":"V-PPA-NMS","st":"5097"},{"tl":"autous","en":"them","gr":"αὐτοὺς","pu":",","pa":"PPro-AM3P","st":"846"},{"tl":"ēnankazon","en":"I was compelling [them]","gr":"ἠνάγκαζον","pu":null,"pa":"V-IIA-1S","st":"315"},{"tl":"blasphēmein","en":"to blaspheme","gr":"βλασφημεῖν","pu":".","pa":"V-PNA","st":"987"},{"tl":"perissōs","en":"Exceedingly","gr":"περισσῶς","pu":null,"pa":"Adv","st":"4057"},{"tl":"te","en":"then","gr":"τε","pu":null,"pa":"Conj","st":"5037"},{"tl":"emmainomenos","en":"being furious","gr":"ἐμμαινόμενος","pu":null,"pa":"V-PPM/P-NMS","st":"1693"},{"tl":"autois","en":"against them","gr":"αὐτοῖς","pu":",","pa":"PPro-DM3P","st":"846"},{"tl":"ediōkon","en":"I kept persecuting [them]","gr":"ἐδίωκον","pu":null,"pa":"V-IIA-1S","st":"1377"},{"tl":"heōs","en":"as far as","gr":"ἕως","pu":null,"pa":"Prep","st":"2193"},{"tl":"kai","en":"even","gr":"καὶ","pu":null,"pa":"Conj","st":"2532"},{"tl":"eis","en":"to","gr":"εἰς","pu":null,"pa":"Prep","st":"1519"},{"tl":"tas","en":" - ","gr":"τὰς","pu":null,"pa":"Art-AFP","st":"3588"},{"tl":"exō","en":"foreign","gr":"ἔξω","pu":null,"pa":"Adv","st":"1854"},{"tl":"poleis","en":"cities","gr":"πόλεις","pu":",","pa":"N-AFP","st":"4172"}],"12":[{"tl":"En","en":"during","gr":"Ἐν","pu":null,"pa":"Prep","st":"1722"},{"tl":"hois","en":"which","gr":"οἷς","pu":",","pa":"RelPro-DNP","st":"3739"},{"tl":"poreuomenos","en":"journeying","gr":"πορευόμενος","pu":null,"pa":"V-PPM/P-NMS","st":"4198"},{"tl":"eis","en":"to","gr":"εἰς","pu":null,"pa":"Prep","st":"1519"},{"tl":"tēn","en":" - ","gr":"τὴν","pu":null,"pa":"Art-AFS","st":"3588"},{"tl":"Damaskon","en":"Damascus","gr":"Δαμασκὸν","pu":null,"pa":"N-AFS","st":"1154"},{"tl":"met’","en":"with","gr":"μετ’","pu":null,"pa":"Prep","st":"3326"},{"tl":"exousias","en":"[the] authority","gr":"ἐξουσίας","pu":null,"pa":"N-GFS","st":"1849"},{"tl":"kai","en":"and","gr":"καὶ","pu":null,"pa":"Conj","st":"2532"},{"tl":"epitropēs","en":"commission","gr":"ἐπιτροπῆς","pu":null,"pa":"N-GFS","st":"2011"},{"tl":"tēs","en":"of","gr":"τῆς","pu":null,"pa":"Art-GFS","st":"3588"},{"tl":"tōn","en":"the","gr":"τῶν","pu":null,"pa":"Art-GMP","st":"3588"},{"tl":"archiereōn","en":"chief priests","gr":"ἀρχιερέων","pu":",","pa":"N-GMP","st":"749"}],"13":[{"tl":"hēmeras","en":"day","gr":"ἡμέρας","pu":null,"pa":"N-GFS","st":"2250"},{"tl":"mesēs","en":"mid","gr":"μέσης","pu":null,"pa":"Adj-GFS","st":"3319"},{"tl":"kata","en":"on","gr":"κατὰ","pu":null,"pa":"Prep","st":"2596"},{"tl":"tēn","en":"the","gr":"τὴν","pu":null,"pa":"Art-AFS","st":"3588"},{"tl":"hodon","en":"road","gr":"ὁδὸν","pu":null,"pa":"N-AFS","st":"3598"},{"tl":"eidon","en":"I saw","gr":"εἶδον","pu":",","pa":"V-AIA-1S","st":"3708"},{"tl":"basileu","en":"O king","gr":"βασιλεῦ","pu":",","pa":"N-VMS","st":"935"},{"tl":"ouranothen","en":"from heaven","gr":"οὐρανόθεν","pu":null,"pa":"Adv","st":"3771"},{"tl":"hyper","en":"above","gr":"ὑπὲρ","pu":",","pa":"Prep","st":"5228"},{"tl":"tēn","en":"the","gr":"τὴν","pu":null,"pa":"Art-AFS","st":"3588"},{"tl":"lamprotēta","en":"brightness","gr":"λαμπρότητα","pu":null,"pa":"N-AFS","st":"2987"},{"tl":"tou","en":"of the","gr":"τοῦ","pu":null,"pa":"Art-GMS","st":"3588"},{"tl":"hēliou","en":"sun","gr":"ἡλίου","pu":",","pa":"N-GMS","st":"2246"},{"tl":"perilampsan","en":"having shone around","gr":"περιλάμψαν","pu":null,"pa":"V-APA-ANS","st":"4034"},{"tl":"me","en":"me","gr":"με","pu":",","pa":"PPro-A1S","st":"1473"},{"tl":"phōs","en":"a light","gr":"φῶς","pu":";","pa":"N-ANS","st":"5457"},{"tl":"kai","en":"and","gr":"καὶ","pu":null,"pa":"Conj","st":"2532"},{"tl":"tous","en":"those","gr":"τοὺς","pu":null,"pa":"Art-AMP","st":"3588"},{"tl":"syn","en":"with","gr":"σὺν","pu":null,"pa":"Prep","st":"4862"},{"tl":"emoi","en":"me","gr":"ἐμοὶ","pu":null,"pa":"PPro-D1S","st":"1473"},{"tl":"poreuomenous","en":"journeying","gr":"πορευομένους","pu":".","pa":"V-PPM/P-AMP","st":"4198"}],"14":[{"tl":"pantōn","en":"All","gr":"πάντων","pu":null,"pa":"Adj-GMP","st":"3956"},{"tl":"te","en":"and","gr":"τε","pu":null,"pa":"Conj","st":"5037"},{"tl":"katapesontōn","en":"having fallen down","gr":"καταπεσόντων","pu":null,"pa":"V-APA-GMP","st":"2667"},{"tl":"hēmōn","en":"of us","gr":"ἡμῶν","pu":null,"pa":"PPro-G1P","st":"1473"},{"tl":"eis","en":"to","gr":"εἰς","pu":null,"pa":"Prep","st":"1519"},{"tl":"tēn","en":"the","gr":"τὴν","pu":null,"pa":"Art-AFS","st":"3588"},{"tl":"gēn","en":"ground","gr":"γῆν","pu":",","pa":"N-AFS","st":"1093"},{"tl":"ēkousa","en":"I heard","gr":"ἤκουσα","pu":null,"pa":"V-AIA-1S","st":"191"},{"tl":"phōnēn","en":"a voice","gr":"φωνὴν","pu":null,"pa":"N-AFS","st":"5456"},{"tl":"legousan","en":"saying","gr":"λέγουσαν","pu":null,"pa":"V-PPA-AFS","st":"3004"},{"tl":"pros","en":"to","gr":"πρός","pu":null,"pa":"Prep","st":"4314"},{"tl":"me","en":"me","gr":"με","pu":null,"pa":"PPro-A1S","st":"1473"},{"tl":"tē","en":"in the","gr":"τῇ","pu":null,"pa":"Art-DFS","st":"3588"},{"tl":"Hebraidi","en":"Hebrew","gr":"Ἑβραΐδι","pu":null,"pa":"Adj-DFS","st":"1446"},{"tl":"dialektō","en":"language","gr":"διαλέκτῳ","pu":",","pa":"N-DFS","st":"1258"},{"tl":"Saoul","en":"Saul","gr":"Σαοὺλ","pu":",","pa":"N-VMS","st":"4549"},{"tl":"Saoul","en":"Saul","gr":"Σαούλ","pu":",","pa":"N-VMS","st":"4549"},{"tl":"ti","en":"why","gr":"τί","pu":null,"pa":"IPro-ANS","st":"5101"},{"tl":"me","en":"Me","gr":"με","pu":null,"pa":"PPro-A1S","st":"1473"},{"tl":"diōkeis","en":"persecute you","gr":"διώκεις","pu":"?","pa":"V-PIA-2S","st":"1377"},{"tl":"sklēron","en":"[It is] hard","gr":"σκληρόν","pu":null,"pa":"Adj-NNS","st":"4642"},{"tl":"soi","en":"for you","gr":"σοι","pu":null,"pa":"PPro-D2S","st":"4771"},{"tl":"pros","en":"against","gr":"πρὸς","pu":null,"pa":"Prep","st":"4314"},{"tl":"kentra","en":"[the] goads","gr":"κέντρα","pu":null,"pa":"N-ANP","st":"2759"},{"tl":"laktizein","en":"to kick","gr":"λακτίζειν","pu":".","pa":"V-PNA","st":"2979"}],"15":[{"tl":"Egō","en":"I","gr":"Ἐγὼ","pu":null,"pa":"PPro-N1S","st":"1473"},{"tl":"de","en":"then","gr":"δὲ","pu":null,"pa":"Conj","st":"1161"},{"tl":"eipa","en":"said","gr":"εἶπα","pu":",","pa":"V-AIA-1S","st":"2036"},{"tl":"Tis","en":"Who","gr":"Τίς","pu":null,"pa":"IPro-NMS","st":"5101"},{"tl":"ei","en":"are You","gr":"εἶ","pu":",","pa":"V-PIA-2S","st":"1510"},{"tl":"Kyrie","en":"Lord","gr":"Κύριε","pu":"?","pa":"N-VMS","st":"2962"},{"tl":"Ho","en":" - ","gr":"Ὁ","pu":null,"pa":"Art-NMS","st":"3588"},{"tl":"de","en":"And","gr":"δὲ","pu":null,"pa":"Conj","st":"1161"},{"tl":"Kyrios","en":"the Lord","gr":"Κύριος","pu":null,"pa":"N-NMS","st":"2962"},{"tl":"eipen","en":"said","gr":"εἶπεν","pu":",","pa":"V-AIA-3S","st":"2036"},{"tl":"Egō","en":"I","gr":"Ἐγώ","pu":null,"pa":"PPro-N1S","st":"1473"},{"tl":"eimi","en":"am","gr":"εἰμι","pu":null,"pa":"V-PIA-1S","st":"1510"},{"tl":"Iēsous","en":"Jesus","gr":"Ἰησοῦς","pu":",","pa":"N-NMS","st":"2424"},{"tl":"hon","en":"whom","gr":"ὃν","pu":null,"pa":"RelPro-AMS","st":"3739"},{"tl":"sy","en":"you","gr":"σὺ","pu":null,"pa":"PPro-N2S","st":"4771"},{"tl":"diōkeis","en":"are persecuting","gr":"διώκεις","pu":".","pa":"V-PIA-2S","st":"1377"}],"16":[{"tl":"alla","en":"But","gr":"ἀλλὰ","pu":null,"pa":"Conj","st":"235"},{"tl":"anastēthi","en":"rise up","gr":"ἀνάστηθι","pu":null,"pa":"V-AMA-2S","st":"450"},{"tl":"kai","en":"and","gr":"καὶ","pu":null,"pa":"Conj","st":"2532"},{"tl":"stēthi","en":"stand","gr":"στῆθι","pu":null,"pa":"V-AMA-2S","st":"2476"},{"tl":"epi","en":"on","gr":"ἐπὶ","pu":null,"pa":"Prep","st":"1909"},{"tl":"tous","en":"the","gr":"τοὺς","pu":null,"pa":"Art-AMP","st":"3588"},{"tl":"podas","en":"feet","gr":"πόδας","pu":null,"pa":"N-AMP","st":"4228"},{"tl":"sou","en":"of you","gr":"σου","pu":";","pa":"PPro-G2S","st":"4771"},{"tl":"eis","en":"for this","gr":"εἰς","pu":null,"pa":"Prep","st":"1519"},{"tl":"touto","en":"purpose","gr":"τοῦτο","pu":null,"pa":"DPro-ANS","st":"3778"},{"tl":"gar","en":"for","gr":"γὰρ","pu":null,"pa":"Conj","st":"1063"},{"tl":"ōphthēn","en":"I have appeared","gr":"ὤφθην","pu":null,"pa":"V-AIP-1S","st":"3708"},{"tl":"soi","en":"to you","gr":"σοι","pu":",","pa":"PPro-D2S","st":"4771"},{"tl":"procheirisasthai","en":"to appoint","gr":"προχειρίσασθαί","pu":null,"pa":"V-ANM","st":"4400"},{"tl":"se","en":"you","gr":"σε","pu":null,"pa":"PPro-A2S","st":"4771"},{"tl":"hypēretēn","en":"a servant","gr":"ὑπηρέτην","pu":null,"pa":"N-AMS","st":"5257"},{"tl":"kai","en":"and","gr":"καὶ","pu":null,"pa":"Conj","st":"2532"},{"tl":"martyra","en":"a witness","gr":"μάρτυρα","pu":null,"pa":"N-AMS","st":"3144"},{"tl":"hōn","en":"of that which","gr":"ὧν","pu":null,"pa":"RelPro-GNP","st":"3739"},{"tl":"te","en":"both","gr":"τε","pu":null,"pa":"Conj","st":"5037"},{"tl":"eides","en":"you have seen","gr":"εἶδές","pu":null,"pa":"V-AIA-2S","st":"3708"},{"tl":"me","en":"of Me","gr":"με","pu":",","pa":"PPro-A1S","st":"1473"},{"tl":"hōn","en":"of the things in which","gr":"ὧν","pu":null,"pa":"RelPro-GNP","st":"3739"},{"tl":"te","en":"then","gr":"τε","pu":null,"pa":"Conj","st":"5037"},{"tl":"ophthēsomai","en":"I will appear","gr":"ὀφθήσομαί","pu":null,"pa":"V-FIP-1S","st":"3708"},{"tl":"soi","en":"to you","gr":"σοι","pu":",","pa":"PPro-D2S","st":"4771"}],"17":[{"tl":"exairoumenos","en":"delivering","gr":"ἐξαιρούμενός","pu":null,"pa":"V-PPM-NMS","st":"1807"},{"tl":"se","en":"you","gr":"σε","pu":null,"pa":"PPro-A2S","st":"4771"},{"tl":"ek","en":"out from","gr":"ἐκ","pu":null,"pa":"Prep","st":"1537"},{"tl":"tou","en":"the","gr":"τοῦ","pu":null,"pa":"Art-GMS","st":"3588"},{"tl":"laou","en":"people","gr":"λαοῦ","pu":null,"pa":"N-GMS","st":"2992"},{"tl":"kai","en":"and","gr":"καὶ","pu":null,"pa":"Conj","st":"2532"},{"tl":"ek","en":"from","gr":"ἐκ","pu":null,"pa":"Prep","st":"1537"},{"tl":"tōn","en":"the","gr":"τῶν","pu":null,"pa":"Art-GNP","st":"3588"},{"tl":"ethnōn","en":"Gentiles","gr":"ἐθνῶν","pu":",","pa":"N-GNP","st":"1484"},{"tl":"eis","en":"to","gr":"εἰς","pu":null,"pa":"Prep","st":"1519"},{"tl":"hous","en":"whom","gr":"οὓς","pu":null,"pa":"RelPro-AMP","st":"3739"},{"tl":"egō","en":"I","gr":"ἐγὼ","pu":null,"pa":"PPro-N1S","st":"1473"},{"tl":"apostellō","en":"am sending","gr":"ἀποστέλλω","pu":null,"pa":"V-PIA-1S","st":"649"},{"tl":"se","en":"you","gr":"σε","pu":",","pa":"PPro-A2S","st":"4771"}],"18":[{"tl":"anoixai","en":"to open","gr":"ἀνοῖξαι","pu":null,"pa":"V-ANA","st":"455"},{"tl":"ophthalmous","en":"eyes","gr":"ὀφθαλμοὺς","pu":null,"pa":"N-AMP","st":"3788"},{"tl":"autōn","en":"of them","gr":"αὐτῶν","pu":",","pa":"PPro-GM3P","st":"846"},{"tl":"tou","en":"that","gr":"τοῦ","pu":null,"pa":"Art-GNS","st":"3588"},{"tl":"epistrepsai","en":"they may turn","gr":"ἐπιστρέψαι","pu":null,"pa":"V-ANA","st":"1994"},{"tl":"apo","en":"from","gr":"ἀπὸ","pu":null,"pa":"Prep","st":"575"},{"tl":"skotous","en":"darkness","gr":"σκότους","pu":null,"pa":"N-GNS","st":"4655"},{"tl":"eis","en":"to","gr":"εἰς","pu":null,"pa":"Prep","st":"1519"},{"tl":"phōs","en":"light","gr":"φῶς","pu":",","pa":"N-ANS","st":"5457"},{"tl":"kai","en":"and","gr":"καὶ","pu":null,"pa":"Conj","st":"2532"},{"tl":"tēs","en":"from the","gr":"τῆς","pu":null,"pa":"Art-GFS","st":"3588"},{"tl":"exousias","en":"power","gr":"ἐξουσίας","pu":null,"pa":"N-GFS","st":"1849"},{"tl":"tou","en":" - ","gr":"τοῦ","pu":null,"pa":"Art-GMS","st":"3588"},{"tl":"Satana","en":"of Satan","gr":"Σατανᾶ","pu":null,"pa":"N-GMS","st":"4567"},{"tl":"epi","en":"to","gr":"ἐπὶ","pu":null,"pa":"Prep","st":"1909"},{"tl":"ton","en":" - ","gr":"τὸν","pu":null,"pa":"Art-AMS","st":"3588"},{"tl":"Theon","en":"God","gr":"Θεόν","pu":",","pa":"N-AMS","st":"2316"},{"tl":"tou","en":"[that]","gr":"τοῦ","pu":null,"pa":"Art-GNS","st":"3588"},{"tl":"labein","en":"may receive","gr":"λαβεῖν","pu":null,"pa":"V-ANA","st":"2983"},{"tl":"autous","en":"they","gr":"αὐτοὺς","pu":null,"pa":"PPro-AM3P","st":"846"},{"tl":"aphesin","en":"forgiveness","gr":"ἄφεσιν","pu":null,"pa":"N-AFS","st":"859"},{"tl":"hamartiōn","en":"of sins","gr":"ἁμαρτιῶν","pu":null,"pa":"N-GFP","st":"266"},{"tl":"kai","en":"and","gr":"καὶ","pu":null,"pa":"Conj","st":"2532"},{"tl":"klēron","en":"[an] inheritance","gr":"κλῆρον","pu":null,"pa":"N-AMS","st":"2819"},{"tl":"en","en":"among","gr":"ἐν","pu":null,"pa":"Prep","st":"1722"},{"tl":"tois","en":"those","gr":"τοῖς","pu":null,"pa":"Art-DMP","st":"3588"},{"tl":"hēgiasmenois","en":"having been sanctified","gr":"ἡγιασμένοις","pu":null,"pa":"V-RPM/P-DMP","st":"37"},{"tl":"pistei","en":"by faith","gr":"πίστει","pu":null,"pa":"N-DFS","st":"4102"},{"tl":"tē","en":"that [is]","gr":"τῇ","pu":null,"pa":"Art-DFS","st":"3588"},{"tl":"eis","en":"in","gr":"εἰς","pu":null,"pa":"Prep","st":"1519"},{"tl":"eme","en":"Me","gr":"ἐμέ","pu":".","pa":"PPro-A1S","st":"1473"}],"19":[{"tl":"Hothen","en":"So then","gr":"Ὅθεν","pu":",","pa":"Conj","st":"3606"},{"tl":"basileu","en":"O king","gr":"βασιλεῦ","pu":null,"pa":"N-VMS","st":"935"},{"tl":"Agrippa","en":"Agrippa","gr":"Ἀγρίππα","pu":",","pa":"N-VMS","st":"67"},{"tl":"ouk","en":"not","gr":"οὐκ","pu":null,"pa":"Adv","st":"3756"},{"tl":"egenomēn","en":"I was","gr":"ἐγενόμην","pu":null,"pa":"V-AIM-1S","st":"1096"},{"tl":"apeithēs","en":"disobedient","gr":"ἀπειθὴς","pu":null,"pa":"Adj-NMS","st":"545"},{"tl":"tē","en":"to the","gr":"τῇ","pu":null,"pa":"Art-DFS","st":"3588"},{"tl":"ouraniō","en":"heavenly","gr":"οὐρανίῳ","pu":null,"pa":"Adj-DFS","st":"3770"},{"tl":"optasia","en":"vision","gr":"ὀπτασίᾳ","pu":",","pa":"N-DFS","st":"3701"}],"20":[{"tl":"alla","en":"but","gr":"ἀλλὰ","pu":null,"pa":"Conj","st":"235"},{"tl":"tois","en":"to those","gr":"τοῖς","pu":null,"pa":"Art-DMP","st":"3588"},{"tl":"en","en":"in","gr":"ἐν","pu":null,"pa":"Prep","st":"1722"},{"tl":"Damaskō","en":"Damascus","gr":"Δαμασκῷ","pu":null,"pa":"N-DFS","st":"1154"},{"tl":"prōton","en":"first","gr":"πρῶτόν","pu":",","pa":"Adv-S","st":"4412"},{"tl":"te","en":"both","gr":"τε","pu":null,"pa":"Conj","st":"5037"},{"tl":"kai","en":"and","gr":"καὶ","pu":null,"pa":"Conj","st":"2532"},{"tl":"Hierosolymois","en":"Jerusalem","gr":"Ἱεροσολύμοις","pu":null,"pa":"N-DNP","st":"2414"},{"tl":"pasan","en":"all","gr":"πᾶσάν","pu":",","pa":"Adj-AFS","st":"3956"},{"tl":"te","en":"and","gr":"τε","pu":null,"pa":"Conj","st":"5037"},{"tl":"tēn","en":"the","gr":"τὴν","pu":null,"pa":"Art-AFS","st":"3588"},{"tl":"chōran","en":"region","gr":"χώραν","pu":null,"pa":"N-AFS","st":"5561"},{"tl":"tēs","en":" - ","gr":"τῆς","pu":null,"pa":"Art-GFS","st":"3588"},{"tl":"Ioudaias","en":"of Judea","gr":"Ἰουδαίας","pu":",","pa":"N-GFS","st":"2449"},{"tl":"kai","en":"and","gr":"καὶ","pu":null,"pa":"Conj","st":"2532"},{"tl":"tois","en":"to the","gr":"τοῖς","pu":null,"pa":"Art-DNP","st":"3588"},{"tl":"ethnesin","en":"Gentiles","gr":"ἔθνεσιν","pu":",","pa":"N-DNP","st":"1484"},{"tl":"apēngellon","en":"I kept declaring","gr":"ἀπήγγελλον","pu":null,"pa":"V-IIA-1S","st":"518"},{"tl":"metanoein","en":"to repent","gr":"μετανοεῖν","pu":null,"pa":"V-PNA","st":"3340"},{"tl":"kai","en":"and","gr":"καὶ","pu":null,"pa":"Conj","st":"2532"},{"tl":"epistrephein","en":"to turn","gr":"ἐπιστρέφειν","pu":null,"pa":"V-ANA","st":"1994"},{"tl":"epi","en":"to","gr":"ἐπὶ","pu":null,"pa":"Prep","st":"1909"},{"tl":"ton","en":" - ","gr":"τὸν","pu":null,"pa":"Art-AMS","st":"3588"},{"tl":"Theon","en":"God","gr":"Θεόν","pu":",","pa":"N-AMS","st":"2316"},{"tl":"axia","en":"worthy","gr":"ἄξια","pu":null,"pa":"Adj-ANP","st":"514"},{"tl":"tēs","en":" - ","gr":"τῆς","pu":null,"pa":"Art-GFS","st":"3588"},{"tl":"metanoias","en":"of repentance","gr":"μετανοίας","pu":null,"pa":"N-GFS","st":"3341"},{"tl":"erga","en":"works","gr":"ἔργα","pu":null,"pa":"N-ANP","st":"2041"},{"tl":"prassontas","en":"doing","gr":"πράσσοντας","pu":".","pa":"V-PPA-AMP","st":"4238"}],"21":[{"tl":"heneka","en":"On account of","gr":"ἕνεκα","pu":null,"pa":"Prep","st":"1752"},{"tl":"toutōn","en":"these things","gr":"τούτων","pu":",","pa":"DPro-GNP","st":"3778"},{"tl":"me","en":"me","gr":"με","pu":null,"pa":"PPro-A1S","st":"1473"},{"tl":"Ioudaioi","en":"the Jews","gr":"Ἰουδαῖοι","pu":null,"pa":"Adj-NMP","st":"2453"},{"tl":"syllabomenoi","en":"having seized","gr":"συλλαβόμενοι","pu":null,"pa":"V-APM-NMP","st":"4815"},{"tl":"onta","en":"being","gr":"[ὄντα]","pu":null,"pa":"V-PPA-AMS","st":"1510"},{"tl":"en","en":"in","gr":"ἐν","pu":null,"pa":"Prep","st":"1722"},{"tl":"tō","en":"the","gr":"τῷ","pu":null,"pa":"Art-DNS","st":"3588"},{"tl":"hierō","en":"temple","gr":"ἱερῷ","pu":",","pa":"N-DNS","st":"2411"},{"tl":"epeirōnto","en":"they were attempting","gr":"ἐπειρῶντο","pu":null,"pa":"V-IIM/P-3P","st":"3987"},{"tl":"diacheirisasthai","en":"to kill","gr":"διαχειρίσασθαι","pu":".","pa":"V-ANM","st":"1315"}],"22":[{"tl":"Epikourias","en":"Help","gr":"Ἐπικουρίας","pu":null,"pa":"N-GFS","st":"1947"},{"tl":"oun","en":"therefore","gr":"οὖν","pu":null,"pa":"Conj","st":"3767"},{"tl":"tychōn","en":"having obtained","gr":"τυχὼν","pu":null,"pa":"V-APA-NMS","st":"5177"},{"tl":"tēs","en":" - ","gr":"τῆς","pu":null,"pa":"Art-GFS","st":"3588"},{"tl":"apo","en":"from","gr":"ἀπὸ","pu":null,"pa":"Prep","st":"575"},{"tl":"tou","en":" - ","gr":"τοῦ","pu":null,"pa":"Art-GMS","st":"3588"},{"tl":"Theou","en":"God","gr":"Θεοῦ","pu":null,"pa":"N-GMS","st":"2316"},{"tl":"achri","en":"unto","gr":"ἄχρι","pu":null,"pa":"Prep","st":"891"},{"tl":"tēs","en":"the","gr":"τῆς","pu":null,"pa":"Art-GFS","st":"3588"},{"tl":"hēmeras","en":"day","gr":"ἡμέρας","pu":null,"pa":"N-GFS","st":"2250"},{"tl":"tautēs","en":"this","gr":"ταύτης","pu":",","pa":"DPro-GFS","st":"3778"},{"tl":"hestēka","en":"I have stood","gr":"ἕστηκα","pu":",","pa":"V-RIA-1S","st":"2476"},{"tl":"martyromenos","en":"bearing witness","gr":"μαρτυρόμενος","pu":null,"pa":"V-PPM/P-NMS","st":"3143"},{"tl":"mikrō","en":"to small","gr":"μικρῷ","pu":null,"pa":"Adj-DMS","st":"3398"},{"tl":"te","en":"both","gr":"τε","pu":null,"pa":"Conj","st":"5037"},{"tl":"kai","en":"and","gr":"καὶ","pu":null,"pa":"Conj","st":"2532"},{"tl":"megalō","en":"to great","gr":"μεγάλῳ","pu":",","pa":"Adj-DMS","st":"3173"},{"tl":"ouden","en":"nothing","gr":"οὐδὲν","pu":null,"pa":"Adj-ANS","st":"3762"},{"tl":"ektos","en":"other","gr":"ἐκτὸς","pu":null,"pa":"Prep","st":"1622"},{"tl":"legōn","en":"saying","gr":"λέγων","pu":null,"pa":"V-PPA-NMS","st":"3004"},{"tl":"hōn","en":"than what","gr":"ὧν","pu":null,"pa":"RelPro-GNP","st":"3739"},{"tl":"te","en":"both","gr":"τε","pu":null,"pa":"Conj","st":"5037"},{"tl":"hoi","en":"the","gr":"οἱ","pu":null,"pa":"Art-NMP","st":"3588"},{"tl":"prophētai","en":"prophets","gr":"προφῆται","pu":null,"pa":"N-NMP","st":"4396"},{"tl":"elalēsan","en":"said","gr":"ἐλάλησαν","pu":null,"pa":"V-AIA-3P","st":"2980"},{"tl":"mellontōn","en":"was about","gr":"μελλόντων","pu":null,"pa":"V-PPA-GNP","st":"3195"},{"tl":"ginesthai","en":"to happen","gr":"γίνεσθαι","pu":",","pa":"V-PNM/P","st":"1096"},{"tl":"kai","en":"and","gr":"καὶ","pu":null,"pa":"Conj","st":"2532"},{"tl":"Mōusēs","en":"Moses","gr":"Μωϋσῆς","pu":",","pa":"N-NMS","st":"3475"}],"23":[{"tl":"ei","en":"that","gr":"εἰ","pu":null,"pa":"Conj","st":"1487"},{"tl":"pathētos","en":"would suffer","gr":"παθητὸς","pu":null,"pa":"Adj-NMS","st":"3805"},{"tl":"ho","en":"the","gr":"ὁ","pu":null,"pa":"Art-NMS","st":"3588"},{"tl":"Christos","en":"Christ","gr":"Χριστός","pu":";","pa":"N-NMS","st":"5547"},{"tl":"ei","en":"as","gr":"εἰ","pu":null,"pa":"Conj","st":"1487"},{"tl":"prōtos","en":"first","gr":"πρῶτος","pu":null,"pa":"Adj-NMS","st":"4413"},{"tl":"ex","en":"through","gr":"ἐξ","pu":null,"pa":"Prep","st":"1537"},{"tl":"anastaseōs","en":"resurrection","gr":"ἀναστάσεως","pu":null,"pa":"N-GFS","st":"386"},{"tl":"nekrōn","en":"from [the] dead","gr":"νεκρῶν","pu":",","pa":"Adj-GMP","st":"3498"},{"tl":"phōs","en":"light","gr":"φῶς","pu":null,"pa":"N-ANS","st":"5457"},{"tl":"mellei","en":"He is about","gr":"μέλλει","pu":null,"pa":"V-PIA-3S","st":"3195"},{"tl":"katangellein","en":"to preach","gr":"καταγγέλλειν","pu":null,"pa":"V-PNA","st":"2605"},{"tl":"tō","en":"to","gr":"τῷ","pu":null,"pa":"Art-DMS","st":"3588"},{"tl":"te","en":"both","gr":"τε","pu":null,"pa":"Conj","st":"5037"},{"tl":"laō","en":"our people","gr":"λαῷ","pu":null,"pa":"N-DMS","st":"2992"},{"tl":"kai","en":"and","gr":"καὶ","pu":null,"pa":"Conj","st":"2532"},{"tl":"tois","en":"to the","gr":"τοῖς","pu":null,"pa":"Art-DNP","st":"3588"},{"tl":"ethnesin","en":"Gentiles","gr":"ἔθνεσιν","pu":".","pa":"N-DNP","st":"1484"}],"24":[{"tl":"Tauta","en":"These things","gr":"Ταῦτα","pu":null,"pa":"DPro-ANP","st":"3778"},{"tl":"de","en":"now","gr":"δὲ","pu":null,"pa":"Conj","st":"1161"},{"tl":"autou","en":"of him","gr":"αὐτοῦ","pu":null,"pa":"PPro-GM3S","st":"846"},{"tl":"apologoumenou","en":"saying in his defense","gr":"ἀπολογουμένου","pu":",","pa":"V-PPM/P-GMS","st":"626"},{"tl":"ho","en":" - ","gr":"ὁ","pu":null,"pa":"Art-NMS","st":"3588"},{"tl":"Phēstos","en":"Festus","gr":"Φῆστος","pu":null,"pa":"N-NMS","st":"5347"},{"tl":"megalē","en":"in a loud","gr":"μεγάλῃ","pu":null,"pa":"Adj-DFS","st":"3173"},{"tl":"tē","en":" - ","gr":"τῇ","pu":null,"pa":"Art-DFS","st":"3588"},{"tl":"phōnē","en":"voice","gr":"φωνῇ","pu":null,"pa":"N-DFS","st":"5456"},{"tl":"phēsin","en":"said","gr":"φησιν","pu":",","pa":"V-PIA-3S","st":"5346"},{"tl":"Mainē","en":"You are insane","gr":"Μαίνῃ","pu":",","pa":"V-PIM/P-2S","st":"3105"},{"tl":"Paule","en":"Paul","gr":"Παῦλε","pu":"!","pa":"N-VMS","st":"3972"},{"tl":"ta","en":"The","gr":"τὰ","pu":null,"pa":"Art-NNP","st":"3588"},{"tl":"polla","en":"great","gr":"πολλά","pu":null,"pa":"Adj-NNP","st":"4183"},{"tl":"se","en":"of you","gr":"σε","pu":null,"pa":"PPro-A2S","st":"4771"},{"tl":"grammata","en":"learning","gr":"γράμματα","pu":",","pa":"N-NNP","st":"1121"},{"tl":"eis","en":"to","gr":"εἰς","pu":null,"pa":"Prep","st":"1519"},{"tl":"manian","en":"insanity","gr":"μανίαν","pu":null,"pa":"N-AFS","st":"3130"},{"tl":"peritrepei","en":"turns [you]","gr":"περιτρέπει","pu":"!","pa":"V-PIA-3S","st":"4062"}],"25":[{"tl":"Ho","en":" - ","gr":"Ὁ","pu":null,"pa":"Art-NMS","st":"3588"},{"tl":"de","en":"But","gr":"δὲ","pu":null,"pa":"Conj","st":"1161"},{"tl":"Paulos","en":"Paul","gr":"Παῦλος","pu":",","pa":"N-NMS","st":"3972"},{"tl":"Ou","en":"Not","gr":"Οὐ","pu":null,"pa":"Adv","st":"3756"},{"tl":"mainomai","en":"I am insane","gr":"μαίνομαι","pu":",","pa":"V-PIM/P-1S","st":"3105"},{"tl":"phēsin","en":"says","gr":"φησίν","pu":",","pa":"V-PIA-3S","st":"5346"},{"tl":"Kratiste","en":"most excellent","gr":"Κράτιστε","pu":null,"pa":"Adj-VMS-S","st":"2903"},{"tl":"Phēste","en":"Festus","gr":"Φῆστε","pu":",","pa":"N-VMS","st":"5347"},{"tl":"alla","en":"but","gr":"ἀλλὰ","pu":null,"pa":"Conj","st":"235"},{"tl":"alētheias","en":"of truth","gr":"ἀληθείας","pu":null,"pa":"N-GFS","st":"225"},{"tl":"kai","en":"and","gr":"καὶ","pu":null,"pa":"Conj","st":"2532"},{"tl":"sōphrosynēs","en":"sobriety","gr":"σωφροσύνης","pu":null,"pa":"N-GFS","st":"4997"},{"tl":"rhēmata","en":"words","gr":"ῥήματα","pu":null,"pa":"N-ANP","st":"4487"},{"tl":"apophthengomai","en":"I utter","gr":"ἀποφθέγγομαι","pu":".","pa":"V-PIM/P-1S","st":"669"}],"26":[{"tl":"epistatai","en":"Understands","gr":"ἐπίσταται","pu":null,"pa":"V-PIM/P-3S","st":"1987"},{"tl":"gar","en":"for","gr":"γὰρ","pu":null,"pa":"Conj","st":"1063"},{"tl":"peri","en":"concerning","gr":"περὶ","pu":null,"pa":"Prep","st":"4012"},{"tl":"toutōn","en":"these things","gr":"τούτων","pu":null,"pa":"DPro-GNP","st":"3778"},{"tl":"ho","en":"the","gr":"ὁ","pu":null,"pa":"Art-NMS","st":"3588"},{"tl":"basileus","en":"king","gr":"βασιλεύς","pu":",","pa":"N-NMS","st":"935"},{"tl":"pros","en":"to","gr":"πρὸς","pu":null,"pa":"Prep","st":"4314"},{"tl":"hon","en":"whom","gr":"ὃν","pu":null,"pa":"RelPro-AMS","st":"3739"},{"tl":"kai","en":"also","gr":"καὶ","pu":null,"pa":"Conj","st":"2532"},{"tl":"parrēsiazomenos","en":"using boldness","gr":"παρρησιαζόμενος","pu":null,"pa":"V-PPM/P-NMS","st":"3955"},{"tl":"lalō","en":"I speak","gr":"λαλῶ","pu":".","pa":"V-PIA-1S","st":"2980"},{"tl":"lanthanein","en":"Are hidden from","gr":"λανθάνειν","pu":null,"pa":"V-PNA","st":"2990"},{"tl":"gar","en":"for","gr":"γὰρ","pu":null,"pa":"Conj","st":"1063"},{"tl":"auton","en":"him","gr":"αὐτὸν","pu":null,"pa":"PPro-AM3S","st":"846"},{"tl":"ti","en":"any","gr":"[τι]","pu":null,"pa":"IPro-ANS","st":"5100"},{"tl":"toutōn","en":"of these things","gr":"τούτων","pu":null,"pa":"DPro-GNP","st":"3778"},{"tl":"ou","en":"not","gr":"οὐ","pu":".","pa":"Adv","st":"3756"},{"tl":"peithomai","en":"I am persuaded","gr":"πείθομαι","pu":null,"pa":"V-PIM/P-1S","st":"3982"},{"tl":"outhen","en":"none","gr":"οὐθέν","pu":null,"pa":"Adj-ANS","st":"3762"},{"tl":"ou","en":"not","gr":"οὐ","pu":null,"pa":"Adv","st":"3756"},{"tl":"gar","en":"for","gr":"γάρ","pu":null,"pa":"Conj","st":"1063"},{"tl":"estin","en":"is","gr":"ἐστιν","pu":null,"pa":"V-PIA-3S","st":"1510"},{"tl":"en","en":"in","gr":"ἐν","pu":null,"pa":"Prep","st":"1722"},{"tl":"gōnia","en":"a corner","gr":"γωνίᾳ","pu":null,"pa":"N-DFS","st":"1137"},{"tl":"pepragmenon","en":"done","gr":"πεπραγμένον","pu":",","pa":"V-RPM/P-NNS","st":"4238"},{"tl":"touto","en":"of these things","gr":"τοῦτο","pu":".","pa":"DPro-NNS","st":"3778"}],"27":[{"tl":"pisteueis","en":"Believe you","gr":"πιστεύεις","pu":",","pa":"V-PIA-2S","st":"4100"},{"tl":"basileu","en":"King","gr":"βασιλεῦ","pu":null,"pa":"N-VMS","st":"935"},{"tl":"Agrippa","en":"Agrippa","gr":"Ἀγρίππα","pu":",","pa":"N-VMS","st":"67"},{"tl":"tois","en":"the","gr":"τοῖς","pu":null,"pa":"Art-DMP","st":"3588"},{"tl":"prophētais","en":"prophets","gr":"προφήταις","pu":"?","pa":"N-DMP","st":"4396"},{"tl":"oida","en":"I know","gr":"οἶδα","pu":null,"pa":"V-RIA-1S","st":"1492"},{"tl":"hoti","en":"that","gr":"ὅτι","pu":null,"pa":"Conj","st":"3754"},{"tl":"pisteueis","en":"you believe","gr":"πιστεύεις","pu":".","pa":"V-PIA-2S","st":"4100"}],"28":[{"tl":"Ho","en":" - ","gr":"Ὁ","pu":null,"pa":"Art-NMS","st":"3588"},{"tl":"de","en":"Then","gr":"δὲ","pu":null,"pa":"Conj","st":"1161"},{"tl":"Agrippas","en":"Agrippa","gr":"Ἀγρίππας","pu":null,"pa":"N-NMS","st":"67"},{"tl":"pros","en":"[said] to","gr":"πρὸς","pu":null,"pa":"Prep","st":"4314"},{"tl":"ton","en":" - ","gr":"τὸν","pu":null,"pa":"Art-AMS","st":"3588"},{"tl":"Paulon","en":"Paul","gr":"Παῦλον","pu":",","pa":"N-AMS","st":"3972"},{"tl":"En","en":"Within","gr":"Ἐν","pu":null,"pa":"Prep","st":"1722"},{"tl":"oligō","en":"so little","gr":"ὀλίγῳ","pu":null,"pa":"Adj-DNS","st":"3641"},{"tl":"me","en":"me","gr":"με","pu":null,"pa":"PPro-A1S","st":"1473"},{"tl":"peitheis","en":"do you persuade","gr":"πείθεις","pu":null,"pa":"V-PIA-2S","st":"3982"},{"tl":"Christianon","en":"a Christian","gr":"Χριστιανὸν","pu":null,"pa":"N-AMS","st":"5546"},{"tl":"poiēsai","en":"to become","gr":"ποιῆσαι","pu":"?","pa":"V-ANA","st":"4160"}],"29":[{"tl":"Ho","en":" - ","gr":"Ὁ","pu":null,"pa":"Art-NMS","st":"3588"},{"tl":"de","en":"And","gr":"δὲ","pu":null,"pa":"Conj","st":"1161"},{"tl":"Paulos","en":"Paul [said]","gr":"Παῦλος","pu":",","pa":"N-NMS","st":"3972"},{"tl":"Euxaimēn","en":"I would wish","gr":"Εὐξαίμην","pu":null,"pa":"V-AOM-1S","st":"2172"},{"tl":"an","en":" - ","gr":"ἂν","pu":null,"pa":"Prtcl","st":"302"},{"tl":"tō","en":" - ","gr":"τῷ","pu":null,"pa":"Art-DMS","st":"3588"},{"tl":"Theō","en":"to God","gr":"Θεῷ","pu":",","pa":"N-DMS","st":"2316"},{"tl":"kai","en":"both","gr":"καὶ","pu":null,"pa":"Conj","st":"2532"},{"tl":"en","en":"in","gr":"ἐν","pu":null,"pa":"Prep","st":"1722"},{"tl":"oligō","en":"a little","gr":"ὀλίγῳ","pu":null,"pa":"Adj-DNS","st":"3641"},{"tl":"kai","en":"and","gr":"καὶ","pu":null,"pa":"Conj","st":"2532"},{"tl":"en","en":"in","gr":"ἐν","pu":null,"pa":"Prep","st":"1722"},{"tl":"megalō","en":"much","gr":"μεγάλῳ","pu":",","pa":"Adj-DNS","st":"3173"},{"tl":"ou","en":"not","gr":"οὐ","pu":null,"pa":"Adv","st":"3756"},{"tl":"monon","en":"only","gr":"μόνον","pu":null,"pa":"Adv","st":"3440"},{"tl":"se","en":"you","gr":"σὲ","pu":null,"pa":"PPro-A2S","st":"4771"},{"tl":"alla","en":"but","gr":"ἀλλὰ","pu":null,"pa":"Conj","st":"235"},{"tl":"kai","en":"also","gr":"καὶ","pu":null,"pa":"Conj","st":"2532"},{"tl":"pantas","en":"all","gr":"πάντας","pu":null,"pa":"Adj-AMP","st":"3956"},{"tl":"tous","en":"those","gr":"τοὺς","pu":null,"pa":"Art-AMP","st":"3588"},{"tl":"akouontas","en":"hearing","gr":"ἀκούοντάς","pu":null,"pa":"V-PPA-AMP","st":"191"},{"tl":"mou","en":"me","gr":"μου","pu":null,"pa":"PPro-G1S","st":"1473"},{"tl":"sēmeron","en":"this day","gr":"σήμερον","pu":",","pa":"Adv","st":"4594"},{"tl":"genesthai","en":"to become","gr":"γενέσθαι","pu":null,"pa":"V-ANM","st":"1096"},{"tl":"toioutous","en":"such","gr":"τοιούτους","pu":null,"pa":"DPro-AMP","st":"5108"},{"tl":"hopoios","en":"as","gr":"ὁποῖος","pu":null,"pa":"RelPro-NMS","st":"3697"},{"tl":"kai","en":"also","gr":"καὶ","pu":null,"pa":"Conj","st":"2532"},{"tl":"egō","en":"I","gr":"ἐγώ","pu":null,"pa":"PPro-N1S","st":"1473"},{"tl":"eimi","en":"am","gr":"εἰμι","pu":",","pa":"V-PIA-1S","st":"1510"},{"tl":"parektos","en":"except","gr":"παρεκτὸς","pu":null,"pa":"Prep","st":"3924"},{"tl":"tōn","en":"the","gr":"τῶν","pu":null,"pa":"Art-GMP","st":"3588"},{"tl":"desmōn","en":"chains","gr":"δεσμῶν","pu":null,"pa":"N-GMP","st":"1199"},{"tl":"toutōn","en":"these","gr":"τούτων","pu":".","pa":"DPro-GMP","st":"3778"}],"30":[{"tl":"Anestē","en":"Rose up","gr":"Ἀνέστη","pu":null,"pa":"V-AIA-3S","st":"450"},{"tl":"te","en":"then","gr":"τε","pu":null,"pa":"Conj","st":"5037"},{"tl":"ho","en":"the","gr":"ὁ","pu":null,"pa":"Art-NMS","st":"3588"},{"tl":"basileus","en":"king","gr":"βασιλεὺς","pu":null,"pa":"N-NMS","st":"935"},{"tl":"kai","en":"and","gr":"καὶ","pu":null,"pa":"Conj","st":"2532"},{"tl":"ho","en":"the","gr":"ὁ","pu":null,"pa":"Art-NMS","st":"3588"},{"tl":"hēgemōn","en":"governor","gr":"ἡγεμὼν","pu":null,"pa":"N-NMS","st":"2232"},{"tl":"hē","en":" - ","gr":"ἥ","pu":null,"pa":"Art-NFS","st":"3588"},{"tl":"te","en":"and","gr":"τε","pu":null,"pa":"Conj","st":"5037"},{"tl":"Bernikē","en":"Bernice","gr":"Βερνίκη","pu":null,"pa":"N-NFS","st":"959"},{"tl":"kai","en":"and","gr":"καὶ","pu":null,"pa":"Conj","st":"2532"},{"tl":"hoi","en":"those","gr":"οἱ","pu":null,"pa":"Art-NMP","st":"3588"},{"tl":"synkathēmenoi","en":"sitting with","gr":"συνκαθήμενοι","pu":null,"pa":"V-PPM/P-NMP","st":"4775"},{"tl":"autois","en":"them","gr":"αὐτοῖς","pu":",","pa":"PPro-DM3P","st":"846"}],"31":[{"tl":"kai","en":"and","gr":"καὶ","pu":null,"pa":"Conj","st":"2532"},{"tl":"anachōrēsantes","en":"having withdrawn","gr":"ἀναχωρήσαντες","pu":",","pa":"V-APA-NMP","st":"402"},{"tl":"elaloun","en":"they began speaking","gr":"ἐλάλουν","pu":null,"pa":"V-IIA-3P","st":"2980"},{"tl":"pros","en":"to","gr":"πρὸς","pu":null,"pa":"Prep","st":"4314"},{"tl":"allēlous","en":"one another","gr":"ἀλλήλους","pu":null,"pa":"RecPro-AMP","st":"240"},{"tl":"legontes","en":"saying","gr":"λέγοντες","pu":null,"pa":"V-PPA-NMP","st":"3004"},{"tl":"hoti","en":" - ","gr":"ὅτι","pu":",","pa":"Conj","st":"3754"},{"tl":"Ouden","en":"Nothing","gr":"Οὐδὲν","pu":null,"pa":"Adj-ANS","st":"3762"},{"tl":"thanatou","en":"of death","gr":"θανάτου","pu":null,"pa":"N-GMS","st":"2288"},{"tl":"ē","en":"or","gr":"ἢ","pu":null,"pa":"Conj","st":"2228"},{"tl":"desmōn","en":"of chains","gr":"δεσμῶν","pu":null,"pa":"N-GMP","st":"1199"},{"tl":"axion","en":"worthy","gr":"ἄξιον","pu":null,"pa":"Adj-ANS","st":"514"},{"tl":"ti","en":"any","gr":"‹τι›","pu":null,"pa":"IPro-ANS","st":"5100"},{"tl":"prassei","en":"is doing","gr":"πράσσει","pu":null,"pa":"V-PIA-3S","st":"4238"},{"tl":"ho","en":"the","gr":"ὁ","pu":null,"pa":"Art-NMS","st":"3588"},{"tl":"anthrōpos","en":"man","gr":"ἄνθρωπος","pu":null,"pa":"N-NMS","st":"444"},{"tl":"houtos","en":"this","gr":"οὗτος","pu":".","pa":"DPro-NMS","st":"3778"}],"32":[{"tl":"Agrippas","en":"Agrippa","gr":"Ἀγρίππας","pu":null,"pa":"N-NMS","st":"67"},{"tl":"de","en":"then","gr":"δὲ","pu":null,"pa":"Conj","st":"1161"},{"tl":"tō","en":"to","gr":"τῷ","pu":null,"pa":"Art-DMS","st":"3588"},{"tl":"Phēstō","en":"Festus","gr":"Φήστῳ","pu":null,"pa":"N-DMS","st":"5347"},{"tl":"ephē","en":"was saying","gr":"ἔφη","pu":",","pa":"V-IIA-3S","st":"5346"},{"tl":"Apolelysthai","en":"Have been released","gr":"Ἀπολελύσθαι","pu":null,"pa":"V-RNM/P","st":"630"},{"tl":"edynato","en":"could","gr":"ἐδύνατο","pu":null,"pa":"V-IIM/P-3S","st":"1410"},{"tl":"ho","en":"the","gr":"ὁ","pu":null,"pa":"Art-NMS","st":"3588"},{"tl":"anthrōpos","en":"man","gr":"ἄνθρωπος","pu":null,"pa":"N-NMS","st":"444"},{"tl":"houtos","en":"this","gr":"οὗτος","pu":",","pa":"DPro-NMS","st":"3778"},{"tl":"ei","en":"if","gr":"εἰ","pu":null,"pa":"Conj","st":"1487"},{"tl":"mē","en":"not","gr":"μὴ","pu":null,"pa":"Adv","st":"3361"},{"tl":"epekeklēto","en":"he had appealed","gr":"ἐπεκέκλητο","pu":null,"pa":"V-LIM-3S","st":"1941"},{"tl":"Kaisara","en":"to Caesar","gr":"Καίσαρα","pu":".","pa":"N-AMS","st":"2541"}]}}